Workbook

Sheet Dataset
A1: ID | B1: Date | C1: Year | D1: Victim Platform | E1: Loss (as reported) | F1: Gross Bridge-Specific Loss (USD) | G1: Loss Normalization Note | H1: Attack Pattern & Root Cause | I1: Source 1 | J1: Source 2 | K1: Source 3 | L1: Evidence Level | M1: Attack Pattern | N1: Primary Functional Domain | O1: Reason (Why This Pattern & Domain) | P1: Scope / Evidence Note | Q1: Enabling Mechanism | R1: Boundary Case | S1: Alternative Pattern | T1: Alternative Domain | U1: Classification Confidence | V1: Coder 2 – Attack Pattern | W1: Coder 2 – Primary Functional Domain | X1: Loss Basis
A2: BR-001 | B2: 46257 | C2: =YEAR(B2) -> 2026 | D2: warp.green ERC-20 Bridge (Chia ↔ Ethereum/Base) | E2: ~$93K | F2: 93000 | H2: A Chia-side Chialisp puzzle bug in the ERC-20 bridge module (the separate CAT bridge, securing assets like wXCH, was unaffected). The attacker minted worthless CAT tokens on Chia and presented them to the trusted validator set as legitimately burned wUSDC. Validators signed off on the fake burn attestations, authorizing the EVM side to release real USDC — draining ~85,000 wUSDC.b and 8,000 wUSDC (~$93K) from the Ethereum/Base bridge contracts, later converted to ETH and moved through Tornado Cash. The team offered the attacker a 10% white-hat bounty for returning 90% of funds within 48 hours; the attacker declined. | I2: https://www.gate.com/news/detail/warpgreen-confirms-erc-20-bridge-vulnerability-offers-attacker-10-white-hat-23695179 | J2: https://hacked.slowmist.io/?c=Bridge | K2: https://xch.today/2026/08/26/a-difficult-week-for-chia-defi-warp-green-tibetswap-and-circuit/ | L2: E2 | M2: Event Injection (EI) | N2: FD-1 Deposit | O2: The attacker fabricated a fake burn signal, a worthless minted token presented as a real burn, and the validator set accepted that fabricated signal as proof of a genuine action without independently confirming it. This is the core Event Injection behavior, a crafted signal accepted as a real bridge event, and for this we have mapped it to Event Injection (EI). A burn is the bridge's mirror image of a deposit, and the forged signal is what fooled that exact deposit-recognition point, so for this we have mapped it to FD-1 Deposit. | Q2: None recorded | R2: No | U2: =IF(L2="E4","Low",IF(OR(R2="Yes",L2="E3"),"Medium","High")) -> High | X2: Bridge-held assets withdrawn
A3: BR-002 | B3: 46255 | C3: =YEAR(B3) -> 2026 | D3: The Sandbox Bridge (SAND / LayerZero OFT — Base & BNB Chain) | E3: ~$1.5M economic impact (~$697K direct vault drain) | F3: 697000 | G3: Reported as Aug 21–22, 2026; start date used.; Direct vault drain only; ~$1.5M "economic impact" (incl. token price effects) excluded. | H3: A configuration flaw, not a LayerZero protocol bug (confirmed by Blockaid). SAND's omnichain fungible token (OFT) contract on Base and BNB Chain exposed an approveAndCall function that let the attacker submit a crafted payload causing the contract to call setDelegate on itself, making the attacker the sole verifier of incoming LayerZero bridge messages for that contract. With that control, the attacker forged bridge messages authorizing mints with no corresponding real burn/lock on Ethereum, minting 50M+ SAND initially and eventually over 339 trillion unbacked SAND across Base/BNB Chain, and redeeming 14,742,341.84 real SAND (~$697K) from the Ethereum vault before the team cut LayerZero peer trust and permanently retired the compromised contracts. Ethereum and Polygon SAND were unaffected. | I3: https://www.sandbox.game/en/blog/august-22-exploit-post-mortem/ | J3: https://crypto.news/sandbox-329-trillion-sand-bridge-exploit-675k-stolen/ | K3: https://cointelegraph.com/news/the-sandbox-compensation-sand-bridge-exploit | L3: E1 | M3: Proof Forgery (PF) | N3: FD-3 Verification | O3: The attacker seized control of the message verification role itself via setDelegate, then used that control to forge bridge messages authorizing mints with no real burn or lock behind them. Forging a message that bypasses the verification gate to release funds without a genuine deposit is the defining behavior of Proof Forgery, and for this we have mapped it to Proof Forgery (PF). The compromised component was specifically who is trusted to verify incoming LayerZero messages, so for this we have mapped it to FD-3 Verification. | Q3: None recorded | R3: No | U3: =IF(L3="E4","Low",IF(OR(R3="Yes",L3="E3"),"Medium","High")) -> High | X3: Bridge-held assets withdrawn
A4: BR-003 | B4: 46253 | C4: =YEAR(B4) -> 2026 | D4: Allbridge (Base CCTP router) | E4: ~$190K | F4: 190000 | H4: Allbridge's new Base router integrated Circle's CCTP, but its receiveCctpMessage handler credited the amount written inside an attested Circle message as a spendable deposit without verifying that USDC had actually been minted/delivered to the bridge. The attacker pre-staged a forged message on Polygon 24 days earlier (Circle's MessageTransmitterV2.sendMessage will attest any payload shaped like a deposit, with no burn/mint attached), then — six seconds after a real, unrelated deposit landed and topped up the router's balance — redeemed the forged message, flash-loaned the remaining shortfall (~$809K) from Aave, and withdrew ~$999K, netting ~$190K after repaying the loan. | I4: https://slowmist.medium.com/a-cross-chain-attack-spanning-one-month-analysis-of-the-allbridge-hack-32a6183bce08 | J4: https://defimon.xyz/blog/allbridge-hack-august-2026 | K4: https://broadchain.info/en/articles/tpeh93 | L4: E2 | M4: Event Injection (EI) | N4: FD-1 Deposit | O4: receiveCctpMessage treated the mere existence of an attested message as proof of a deposit, without checking that the funds it described had actually been minted or delivered. Accepting a fake deposit signal as real, with no genuine funds behind it, is the Event Injection pattern, and for this we have mapped it to Event Injection (EI). The vulnerable check is exactly the one meant to confirm a genuine deposit occurred before crediting a balance, so for this we have mapped it to FD-1 Deposit. | Q4: Flash loan | R4: Yes | S4: Proof Forgery (PF) | T4: FD-3 Verification | U4: =IF(L4="E4","Low",IF(OR(R4="Yes",L4="E3"),"Medium","High")) -> Medium | X4: Bridge-held assets withdrawn
A5: BR-004 | B5: 46243 | C5: =YEAR(B5) -> 2026 | D5: Coreum/tx XRP Ledger Bridge | E5: $200K | F5: 200000 | H5: The bridge's relayer software watched the bridge account's transaction history for payments carrying a "Coreum recipient" memo and treated a matching memo as proof of deposit — without ever checking that the payment's destination was actually the bridge address. Since the bridge itself issues the wrapped Coreum token on the XRP Ledger, the attacker simply moved that wrapped token between two wallets they controlled, attached a fake deposit memo, and the transaction showed up in the bridge account's own history. 21 relayers attested the phantom deposit; a 17-of-28 multisig quorum then co-signed 94 real XRP withdrawals over 97 minutes, draining 99.7% of the bridge's XRP reserve. All relayers ran the same unpatched code, so "independent" signers reached identical (wrong) conclusions. | I5: https://en.cryptonomist.ch/2026/08/12/xrp-coreum-bridge-hack/ | J5: https://sigintzero.com/blog/coreum-bridge-200k-xrp-rippling-deposit-forgery | K5: https://shattered.io/coreum-bridge-hack-200k-xrp-2026/ | L5: E2 | M5: Event Injection (EI) | N5: FD-1 Deposit | O5: Relayers accepted a self-sent transfer carrying a fake deposit memo as proof of a real deposit, without checking the transaction actually went to the bridge address. A fabricated deposit signal accepted at face value is the Event Injection pattern, and for this we have mapped it to Event Injection (EI). The flaw is in how a deposit is recognized and attested in the first place, so for this we have mapped it to FD-1 Deposit. | Q5: None recorded | R5: No | U5: =IF(L5="E4","Low",IF(OR(R5="Yes",L5="E3"),"Medium","High")) -> High | X5: Bridge-held assets withdrawn
A6: BR-005 | B6: 46226 | C6: =YEAR(B6) -> 2026 | D6: Verus-Ethereum Bridge (2nd incident, repeat attack) | E6: ~$7.54M | F6: 7540000 | H6: The same vulnerability class as the May 18, 2026 Verus-Ethereum Bridge incident (see that record), reused against the same contract and entry path (submitImports) just two weeks after recovered funds from the May attack had been redeposited into the bridge — strongly suggesting the original fix was incomplete or the patch was never fully deployed. A different attacker, using a new wallet, drained ETH, tBTC, USDC, USDT, EURC, MKR, and scrvUSD. | I6: https://www.certik.com/blog/verus-incident-analysis | J6: https://sigintzero.com/blog/verus-bridge-7-5m-state-root-parser-divergence | K6: https://www.cryptotimes.io/2026/07/26/crypto-loses-over-47m-in-a-week-as-afx-trade-wanchain-verus-get-hacked/ | L6: E2 | M6: Proof Forgery (PF) | N6: FD-3 Verification | O6: submitImports confirmed a transfer hash existed but never checked that the value was actually backed by locked collateral on Verus, so the verification step accepted an unbacked claim as valid. Bypassing the verification check to release funds with no genuine backing is Proof Forgery, and for this we have mapped it to Proof Forgery (PF). The flaw lives in the bridge's cross-chain transfer verification function, so for this we have mapped it to FD-3 Verification. | Q6: None recorded | R6: No | U6: =IF(L6="E4","Low",IF(OR(R6="Yes",L6="E3"),"Medium","High")) -> High | X6: Bridge-held assets withdrawn
A7: BR-006 | B7: 46225 | C7: =YEAR(B7) -> 2026 | D7: AFX Trade (Arbitrum custodial bridge) | E7: ~$24.15M | F7: 24150000 | H7: A validator private-key compromise, similar in kind to IoTeX. The attacker obtained private keys belonging to five of AFX's bridge validators — enough to reach the quorum threshold required to approve a withdrawal. The bridge contract did have a 200-second challenge period meant to let anyone flag a suspicious pending withdrawal, but nobody filed a challenge in time, and the contract auto-finalized the fraudulent transaction. | I7: https://lazarus.day/reports/a-detailed-post-mortem-on-the-afx-security-incident-P8mpR/ | J7: https://www.coindesk.com/tech/2026/07/23/arbitrum-based-afx-trade-drained-of-usd24-million-after-bridge-keys-compromised | K7: https://en.cryptonomist.ch/2026/07/31/afx-bridge-exploit-recovery/ | L7: E2 | M7: Credential Seizure (CS) | N7: FD-5 Governance & Operations | O7: The attacker obtained private keys for enough bridge validators to meet the withdrawal quorum, so the contract was simply following its own rules when it accepted signatures it had no way of knowing were stolen. Using a genuinely stolen signing credential to authorize a transaction, rather than exploiting any code flaw, is the Credential Seizure pattern, and for this we have mapped it to Credential Seizure (CS). Validator signing keys are part of the bridge's persistent operational control plane, so for this we have mapped it to FD-5 Governance & Operations. | Q7: None recorded | R7: No | U7: =IF(L7="E4","Low",IF(OR(R7="Yes",L7="E3"),"Medium","High")) -> High | X7: Bridge-held assets withdrawn
A8: BR-007 | B8: 46223 | C8: =YEAR(B8) -> 2026 | D8: Wanchain (Cardano ↔ BNB Chain bridge, NIGHT token) | E8: $9–13M | F8: 9000000 | G8: Reported range $9–13M; conservative lower bound used. | H8: A message-encoding ambiguity in the bridge's TreasuryCheck validator. The contract signed off on withdrawals by concatenating 14 different variable-length fields into one message with no separators or length markers — meaning two different amounts could produce byte sequences that looked identical to the signature check. The attacker took a legitimate MPC-signed authorization for a tiny withdrawal (~3,110 NIGHT) and shifted the byte boundary between two number fields so the same signature also validated a withdrawal over 65,000 times larger. | I8: https://medium.com/@wanchain_org/cardano-bnb-chain-bridge-incident-post-mortem-353e465276e7 | J8: https://blocksec.com/blog/web3-security-allbridge-wanchain-exploits | K8: https://www.cryptotimes.io/insights/wanchain-night-bridge-exploit-signature-flaw/ | L8: E1 | M8: Proof Forgery (PF) | N8: FD-3 Verification | O8: The flaw was in how the TreasuryCheck validator authenticated a signed withdrawal message. An encoding ambiguity let one genuine signature validate two very different amounts, meaning the signature check approved an unauthorized value. A flaw in the message authentication mechanism that lets an unauthorized value pass as valid is Proof Forgery, and for this we have mapped it to Proof Forgery (PF). TreasuryCheck is the component responsible for confirming a withdrawal request is authentic before it executes, so for this we have mapped it to FD-3 Verification. | Q8: None recorded | R8: No | U8: =IF(L8="E4","Low",IF(OR(R8="Yes",L8="E3"),"Medium","High")) -> High | X8: Bridge-held assets withdrawn
A9: BR-008 | B9: 46222 | C9: =YEAR(B9) -> 2026 | D9: Allbridge Core (Solana stablecoin pools) | E9: ~$1.65M | F9: 1650000 | G9: Reported as Jul 19–20, 2026; start date used. | H9: A flash-loan price manipulation attack on the bridge's internal liquidity accounting. The attacker flash-borrowed $1.12M in USDC, then ran a rapid sequence of same-asset stablecoin swaps specifically designed to break the pool's internal virtual-balance math, severely mispricing USDT relative to USDC. They then withdrew a hugely outsized amount of USDC for a tiny amount of USDT, repaid the flash loan, and bridged the profit to Ethereum. Notably, this was the second time Allbridge suffered nearly this exact class of flash-loan attack. | I9: https://outposts.io/article/allbridge-core-resumes-operations-after-dollar165m-security-2073cf35-cbcf-40c2-9d6b-de033aaf5528 | J9: https://blocksec.com/blog/web3-security-allbridge-wanchain-exploits | K9: https://www.coindesk.com/business/2026/07/20/cross-chain-protocol-allbridge-halts-after-usd1-65-million-flash-loan-exploit | L9: E2 | M9: Economic-State Manipulation (ESM) | N9: FD-4 Execution | O9: The attacker used borrowed capital within a single transaction to break the pool's internal virtual-balance math, mispricing USDT against USDC, and then extracted an outsized withdrawal before repaying the loan. The object being manipulated is the bridge's economic state, its pool balances and the internal pricing derived from them; the flash loan is only the capital source that made the manipulation affordable, not the vulnerability itself. Distorting the economic state a bridge relies on to price or authorize a release, and extracting value from that distortion, is the Economic-State Manipulation pattern, and for this we have mapped it to Economic-State Manipulation (ESM). The manipulated pricing logic lives inside the function that actually executes withdrawals against pool reserves, so for this we have mapped it to FD-4 Execution. | Q9: Flash loan | R9: No | U9: =IF(L9="E4","Low",IF(OR(R9="Yes",L9="E3"),"Medium","High")) -> High | X9: Bridge-held assets withdrawn
A10: BR-009 | B10: 46220 | C10: =YEAR(B10) -> 2026 | D10: Across Protocol (Solana relayer) | E10: ~$4.5M paid out of ~$41.7M attempted | F10: 4500000 | G10: Amount actually paid out; ~$41.7M attempted but not realised excluded. | H10: A bug in off-chain relayer software, not in any on-chain contract. Across's Solana relayer trusted any inner instruction addressed through a specific program authority as a genuine "deposit" event, without checking a required 8-byte Anchor "event discriminator" that distinguishes real events from lookalikes. The attacker deployed a wrapper program that called a harmless read-only function while smuggling in 1,627 completely fabricated deposit events — no real funds ever moved on Solana — and the relayer paid out real capital against 581 of these phantom deposits before the hole was patched roughly 5 hours later. | I10: https://github.com/across-protocol/sdk/commit/2e2f9d9d1f9efdd48866bd04e27efadedc548142 | J10: https://www.gate.com/news/detail/across-solana-relayer-lost-45m-in-forged-deposit-attack-on-july-17-22917844 | K10: https://www.panews.io/articles/019f973d-a5ad-763c-b84f-6759531a170e | L10: E1 | M10: Event Injection (EI) | N10: FD-2 Relay | O10: The relayer paid out against 1,627 completely fabricated deposit events from a rogue program, having skipped the discriminator check that would have proven those events came from the real deposit program. Fabricated events accepted as genuine bridge activity is the Event Injection pattern, and for this we have mapped it to Event Injection (EI). The bug lived specifically in the off-chain relayer's own event validation code, not in how the source contract emits deposit events, so for this we have mapped it to FD-2 Relay rather than FD-1 Deposit. | P10: Official artefact is the protocol's own fix commit (SDK repository) rather than a written post-mortem. | Q10: None recorded | R10: No | U10: =IF(L10="E4","Low",IF(OR(R10="Yes",L10="E3"),"Medium","High")) -> High | X10: Bridge-held assets withdrawn
A11: BR-010 | B11: 46218 | C11: =YEAR(B11) -> 2026 | D11: TeleSwap (Bitcoin bridge) | E11: ~$735K | F11: 735000 | H11: A SPV-based Bitcoin↔EVM bridge whose Bitcoin-side hot wallet was drained through unspecified suspicious outflows (root cause not publicly disclosed by the team even days later). Stolen BTC was swapped to ETH via Chainflip and laundered through Tornado Cash. | I11: https://indagolabs.eu/news/tracing-the-teleswap-exploit-deanonymizing-tornado-cash-outflows-with-our-tool-multichain-detective/ | J11: https://hacked.slowmist.io/?c=Bridge&page=1 | K11: https://www.panews.io/articles/019f7ff7-69eb-72dd-84c5-2fadae2a43e9 | L11: E4 | M11: Credential Seizure (CS) | N11: FD-5 Governance & Operations | O11: The loss pattern, a Bitcoin-side hot wallet drained through unexplained outflows, matches a private key or hot wallet compromise rather than a smart-contract bug, since no on-chain logic flaw has been identified or disclosed. Funds moving out through a compromised custody credential rather than an exploited contract function is the Credential Seizure pattern, and for this we have mapped it to Credential Seizure (CS). Hot-wallet key custody is an off-chain operational control asset, so for this we have mapped it to FD-5 Governance & Operations. | P11: Root cause not publicly disclosed; CS/FD-5 classification is inferred from on-chain outflow behaviour. Re-check if a post-mortem is published. | Q11: None recorded | R11: No | U11: =IF(L11="E4","Low",IF(OR(R11="Yes",L11="E3"),"Medium","High")) -> Low | X11: Bridge-held assets withdrawn
A12: BR-011 | B12: 46160 | C12: =YEAR(B12) -> 2026 | D12: Verus-Ethereum Bridge | E12: ~$11.4–11.58M | F12: 11400000 | G12: Reported range $11.4–11.58M; conservative lower bound used. | H12: A missing validation check in the bridge's import/export verification function (checkExportAndTransfers/submitImports), which confirmed a transfer hash existed but never verified the value was actually backed by locked assets on the Verus source chain. The attacker triggered unbacked Ethereum-side payouts with nothing collateralizing them on the source side | I12: https://www.halborn.com/blog/post/explained-the-verus-ethereum-bridge-hack-may-2026 | J12: https://cryptopotato.com/hacker-steals-over-11m-from-verus-ethereum-bridge/ | K12: https://web.archive.org/web/20260518134150/https://www.theblock.co/post/401571/verus-ethereum-bridge-exploit | L12: E2 | M12: Proof Forgery (PF) | N12: FD-3 Verification | O12: checkExportAndTransfers and submitImports confirmed a transfer hash existed but never verified the value was backed by locked assets on the source chain, so an unbacked claim passed verification. Passing an unbacked claim through the verification gate is Proof Forgery, and for this we have mapped it to Proof Forgery (PF). The missing check sits directly inside the bridge's import and export verification function, so for this we have mapped it to FD-3 Verification. | Q12: None recorded | R12: No | U12: =IF(L12="E4","Low",IF(OR(R12="Yes",L12="E3"),"Medium","High")) -> High | X12: Bridge-held assets withdrawn
A13: BR-012 | B13: 46157 | C13: =YEAR(B13) -> 2026 | D13: THORChain | E13: $10.7M | F13: 10700000 | H13: Not a smart-contract bug at all — a cryptographic attack on THORChain's threshold signature scheme (GG20/TSS), which is supposed to ensure no single validator ever holds a full vault private key. A newly-joined malicious validator registered a deliberately malformed cryptographic key (missing a soundness check THORChain's library should have enforced) and, over two days of normal signing activity, harvested leaked fragments of other validators' key shares until they could reconstruct the entire vault's private key and sign an unauthorized withdrawal directly. | I13: https://blog.thorchain.org/thorchain-exploit-report-1 | J13: https://www.quillaudits.com/blog/hack-analysis/thorchain-gg20-hack | K13: https://blog.thorchain.org/thorchain-exploit-report-2 | L13: E1 | M13: Credential Seizure (CS) | N13: FD-5 Governance & Operations | O13: However unusual the method, the end result was the same as a stolen key. The attacker reconstructed a validator vault's actual private key by harvesting leaked key-share fragments over two days, then used that genuine key to sign an unauthorized withdrawal directly. Signing with a real, if illegitimately obtained, private key is the Credential Seizure pattern, and for this we have mapped it to Credential Seizure (CS). A reconstructed signing key is still a signing credential, the persistent control-plane asset this domain covers, so for this we have mapped it to FD-5 Governance & Operations. | Q13: None recorded | R13: No | U13: =IF(L13="E4","Low",IF(OR(R13="Yes",L13="E3"),"Medium","High")) -> High | X13: Bridge-held assets withdrawn
A14: BR-013 | B14: 46139 | C14: =YEAR(B14) -> 2026 | D14: ZetaChain | E14: ~$334K (internal wallets only) | F14: 334000 | H14: Three chained weaknesses in ZetaChain's GatewayEVM cross-chain messaging contract: (1) the sending side allowed anyone to trigger arbitrary cross-chain calls with no access control, (2) the receiving side would execute almost any instruction including transferFrom, and (3) some wallets had granted the gateway unlimited token approvals that were never revoked. The attacker chained all three to drain internal team wallets (no user funds affected) across four chains. | I14: https://www.theblock.co/post/399315/zetachain-post-mortem | J14: https://blog.solidityscan.com/zetachain-gateway-hack-analysis/ | K14: https://www.cryptotimes.io/2026/04/29/how-a-perfect-storm-of-3-bugs-led-to-zetachains-333k-gatewayevm-exploit/ | L14: E2 | M14: Logic Exploitation (LE) | N14: FD-4 Execution | O14: The root cause is a chain of missing access-control and input-validation checks in the GatewayEVM contract's own code. The contract did exactly what it was coded to do, it just never should have allowed an arbitrary instruction like transferFrom to be triggered this way. A structural coding flaw exploited by using the contract exactly as designed is the Logic Exploitation pattern, and for this we have mapped it to Logic Exploitation (LE). The flaw is in the destination-side function that actually executes the incoming cross-chain instruction, so for this we have mapped it to FD-4 Execution. | Q14: None recorded | R14: No | U14: =IF(L14="E4","Low",IF(OR(R14="Yes",L14="E3"),"Medium","High")) -> High | X14: Wallet funds drained (approvals or redirection)
A15: BR-014 | B15: 46130 | C15: =YEAR(B15) -> 2026 | D15: Kelp DAO / LayerZero | E15: ~$292M drained + ~$236M recycled through lending protocols | F15: 292000000 | G15: Bridge drain only; ~$236M subsequently borrowed on lending protocols is downstream (non-bridge) impact and excluded. | H15: The largest 2026 incident. An attacker compromised the trust assumptions behind LayerZero's off-chain Decentralized Verifier Network (DVN) — via RPC-layer poisoning — to forge a cross-chain proof and mint 116,500 fake rsETH out of nothing. They then used that fake collateral across Aave, Compound, and Euler to borrow ~$236M in real assets before anyone could react, triggering a bad-debt crisis across multiple lending protocols and chains | I15: https://layerzero.network/publications/kelpdao-incident-report.pdf | J15: https://www.halborn.com/blog/post/explained-the-kelp-dao-hack-april-2026 | K15: https://www.chainalysis.com/blog/kelpdao-bridge-exploit-april-2026/ | L15: E1 | M15: Proof Forgery (PF) | N15: FD-3 Verification | O15: The attacker compromised LayerZero's off-chain DVN verification layer to forge a cryptographically valid-looking cross-chain proof and mint fake rsETH with no genuine deposit behind it. Forging a valid-looking proof to obtain an unbacked release is the textbook Proof Forgery pattern, and for this we have mapped it to Proof Forgery (PF). The DVN is the component whose entire job is to verify that a claimed cross-chain state transition really happened, so for this we have mapped it to FD-3 Verification. | P15: Exploited component is LayerZero DVN verification of the rsETH bridge route; lending-market contagion is out of scope. | Q15: RPC poisoning | R15: Yes | S15: Infrastructure Hijacking (IH) | T15: FD-5 Governance & Operations | U15: =IF(L15="E4","Low",IF(OR(R15="Yes",L15="E3"),"Medium","High")) -> Medium | X15: Value of unbacked minted assets
A16: BR-015 | B16: 46125 | C16: =YEAR(B16) -> 2026 | D16: Hyperbridge / Polkadot (DOT) | E16: $2.5 Million | F16: 2500000 | H16: Proof Verification Flaw: Attacker exploited proof verification logic to forge cross-chain messages and mint 1 billion DOT on Ethereum. | I16: https://blog.hyperbridge.network/april-13-post-mortem/ | J16: https://coinmarketcap.com/academy/article/hyperbridge-exploit-mints-1b-dot-tokens-in-attack-certik-reports | K16: https://anomly.rs/hyperbridge-forged-postrequest | L16: E1 | M16: Proof Forgery (PF) | N16: FD-3 Verification | O16: The attacker exploited the bridge's proof verification logic directly to forge cross-chain messages that let them mint 1 billion DOT with no genuine deposit on the source side. Exploiting the verification logic itself to forge a message is Proof Forgery, and for this we have mapped it to Proof Forgery (PF). The exploited function is the one responsible for confirming that a minting message is backed by a real cross-chain transfer, so for this we have mapped it to FD-3 Verification. | Q16: None recorded | R16: No | U16: =IF(L16="E4","Low",IF(OR(R16="Yes",L16="E3"),"Medium","High")) -> High | X16: Reported figure; basis not specified
A17: BR-016 | B17: 46094 | C17: =YEAR(B17) -> 2026 | D17: Messina Bridge (Opulous/OPUL) | E17: $47.5 Million | F17: 47500000 | H17: ~475 million OPUL drained. A signature-replay/multiplication flaw in the bridge's hop() function. Messina's Guardian network signs any valid on-chain event without checking business logic. The hop() function let an attacker take one legitimately-signed cross-chain approval (VAA) and repeatedly feed it back into hop() to mint a new legitimately-signed VAA for the same underlying deposit — over and over, multiplying one deposit into 143 valid claims. Each was cashed out on a different chain, draining escrow across Arbitrum, Ethereum, and BSC and collapsing the OPUL token to the point the project shut down entirely | I17: https://opulous.org/hack-report | L17: E3 | M17: Logic Exploitation (LE) | N17: FD-4 Execution | O17: The Guardians' signatures on each VAA were completely genuine. The bug was that hop() never marked a used VAA as spent, so the same real approval could be replayed to mint new valid claims 143 times over. A missing state-invalidation check exploited by reusing the contract's own logic as written is Logic Exploitation, and for this we have mapped it to Logic Exploitation (LE). The missing check lives in the function that executes each cross-chain hop or claim, not in the signature verification step itself, so for this we have mapped it to FD-4 Execution. | P17: Single official source (project hack report); satisfies the official post-mortem rule. | Q17: None recorded | R17: No | U17: =IF(L17="E4","Low",IF(OR(R17="Yes",L17="E3"),"Medium","High")) -> Medium | X17: Bridge-held assets withdrawn
A18: BR-017 | B18: 46074 | C18: =YEAR(B18) -> 2026 | D18: IoTeX (ioTube) | E18: $4.3 Million | F18: 4300000 | H18: Key Compromise: Unauthorized access to the private key managing the Validator contract on the Ethereum side. | I18: https://iotex.io/blog/security-incident-update-iotube-bridge-exploit-and-recovery-roadmap/ | L18: E3 | M18: Credential Seizure (CS) | N18: FD-5 Governance & Operations | O18: The attacker gained unauthorized access to the private key controlling the Ethereum-side Validator contract and used it directly to mint and move funds. Using a stolen private key to authorize the action is the Credential Seizure pattern, and for this we have mapped it to Credential Seizure (CS). That validator key is a persistent administrative credential, not a one-off transaction bug, so for this we have mapped it to FD-5 Governance & Operations. | P18: Single official source (project incident update); satisfies the official post-mortem rule. | Q18: None recorded | R18: No | U18: =IF(L18="E4","Low",IF(OR(R18="Yes",L18="E3"),"Medium","High")) -> Medium | X18: Reported figure; basis not specified
A19: BR-018 | B19: 46054 | C19: =YEAR(B19) -> 2026 | D19: CrossCurve | E19: $3 Million | F19: 3000000 | H19: Validation Flaw: Bugs in processing cross-chain messages from Axelar allowed forged messages to authorize fund releases without real deposits. A missing access-control check in a cross-chain messaging integration. CrossCurve's ReceiverAxelar contract inherited a function called expressExecute() from the Axelar SDK but never added the validation that normally confirms a message actually came through Axelar's Gateway. The only check left was "has this command ID been used before" — trivially bypassed by generating a fresh, unused ID. The attacker forged a cross-chain message claiming to be a legitimate unlock instruction and drained PortalV2 escrow contracts on both Ethereum and Arbitrum. | I19: https://crosscurve.medium.com/faq-user-questions-following-the-crosscurve-bridge-exploit-84c7dcc7a64b | J19: https://cantina.xyz/blog/crosscurve-bridge-hack-axelar-expressexecute | K19: https://www.halborn.com/blog/post/explained-the-crosscurve-hack-february-2026 | L19: E1 | M19: Proof Forgery (PF) | N19: FD-3 Verification | O19: The missing access-control check meant the destination contract would accept any freshly generated message as a legitimate Axelar-relayed instruction. The attacker forged an unlock message that was never actually verified against Axelar's Gateway. Forging a message that slips past a broken verification check is Proof Forgery, and for this we have mapped it to Proof Forgery (PF). The missing check sat directly inside the function responsible for validating that an incoming cross-chain message is authentic, so for this we have mapped it to FD-3 Verification. | Q19: None recorded | R19: No | U19: =IF(L19="E4","Low",IF(OR(R19="Yes",L19="E3"),"Medium","High")) -> High | X19: Bridge-held assets withdrawn
A20: BR-019 | B20: 46043 | C20: =YEAR(B20) -> 2026 | D20: Saga (SagaEVM) | E20: $7 Million | F20: 7000000 | H20: Message Spoofing: Attackers crafted custom IBC (Inter-Blockchain Communication) message payloads to bypass collateral verification in the ICS20 precompile bridge, minting Saga Dollar (DUSD) stablecoins with no real cross-chain collateral behind them. | I20: https://www.halborn.com/blog/post/explained-the-sagaevm-hack-january-2026 | J20: https://www.theblock.co/post/386638/sagaevm-suffers-exploit | L20: E2 | M20: Proof Forgery (PF) | N20: FD-3 Verification | O20: The attacker crafted a custom IBC message specifically to bypass the collateral verification check in the ICS20 precompile, letting the bridge accept a forged proof of backing that didn't exist. Crafting a message specifically to bypass a verification check is Proof Forgery, and for this we have mapped it to Proof Forgery (PF). The collateral check that was bypassed is the bridge's core verification gate for minting, so for this we have mapped it to FD-3 Verification. | P20: Second independent source (The Block) added to satisfy the evidence rule. | Q20: None recorded | R20: No | U20: =IF(L20="E4","Low",IF(OR(R20="Yes",L20="E3"),"Medium","High")) -> High | X20: Reported figure; basis not specified
A21: BR-020 | B21: 45957 | C21: =YEAR(B21) -> 2025 | D21: 402bridge | E21: $17,693 | F21: 17693 | H21: A leaked admin key stored insecurely on an internet-connected server. The x402 payment/bridge protocol needed an admin private key on its backend to process minting requests — and that key sat on a networked server rather than in cold/secure storage. Once leaked, an attacker transferred contract ownership to themselves and called an internal transferUserToken function to drain USDC from over 200 wallets that had granted the contract unlimited token approvals. | I21: https://www.cryptotimes.io/2025/10/28/402bridge-exploited-for-17k-in-private-key-leak-amid-x402-trend/ | J21: https://crypto.news/402bridge-hack-leads-to-over-200-users-drained-of-usdc/ | K21: https://www.bitget.com/news/detail/12560605057036 | L21: E2 | M21: Credential Seizure (CS) | N21: FD-5 Governance & Operations | O21: A leaked admin private key let the attacker transfer contract ownership to themselves and call a privileged internal function directly. No contract logic was tricked, the admin credential itself was stolen. A stolen administrative credential used to seize ownership and call privileged functions is Credential Seizure, and for this we have mapped it to Credential Seizure (CS). An admin key with ownership transfer rights is a core piece of the bridge's governance and operational control, so for this we have mapped it to FD-5 Governance & Operations. | Q21: None recorded | R21: No | U21: =IF(L21="E4","Low",IF(OR(R21="Yes",L21="E3"),"Medium","High")) -> High | X21: Wallet funds drained (approvals or redirection)
A22: BR-021 | B22: 45924 | C22: =YEAR(B22) -> 2025 | D22: GriffinAI (GAIN token, LayerZero bridge) | E22: ~$3 Million | F22: 3000000 | H22: An admin EOA compromise combined with a LayerZero peer-trust bypass. Less than 24 hours after GAIN's Binance Alpha launch, an attacker compromised an admin wallet on BNB Chain (likely via phishing) and called setPeer, designating a malicious Ethereum contract as a trusted LayerZero peer for the real GAIN OFT contract. The attacker deployed a fake token on Ethereum and "bridged" 5 billion of it through the now-poisoned peer connection — LayerZero's messaging faithfully relayed the mint instruction, and the legitimate BNB Chain GAIN contract minted 5 billion real GAIN tokens against nothing. The attacker sold ~2.8% on PancakeSwap for ~$3M before the token collapsed 90%; proceeds were laundered through deBridge and Tornado Cash. | I22: https://www.quillaudits.com/blog/hack-analysis/griffin-ai-exploit | J22: https://blog.verichains.io/p/deep-dive-into-the-gain-project-incident | K22: https://rekt.news/griffinai-rekt | L22: E2 | M22: Proof Forgery (PF) | N22: FD-3 Verification | O22: Once the admin wallet was compromised, the attacker's real move was to make a malicious contract a trusted LayerZero peer and then forge a bridge message from that fake peer, the same seize the verifier then forge the message pattern as The Sandbox. Forging a bridge message through a hijacked trust relationship to mint unbacked tokens is Proof Forgery, and for this we have mapped it to Proof Forgery (PF). Peer trust is exactly the mechanism LayerZero uses to verify that an incoming message is legitimate, so for this we have mapped it to FD-3 Verification. | Q22: Phishing (suspected) | R22: Yes | S22: Credential Seizure (CS) | T22: FD-5 Governance & Operations | U22: =IF(L22="E4","Low",IF(OR(R22="Yes",L22="E3"),"Medium","High")) -> Medium | X22: Real assets obtained with unbacked tokens
A23: BR-022 | B23: 45923 | C23: =YEAR(B23) -> 2025 | D23: Seedify SFUND Bridge | E23: $1.2 million | F23: 1200000 | H23: A compromised developer key on a bridge contract that should never have allowed unbacked minting. Attackers (linked to North Korea's Lazarus Group) obtained a Seedify developer's private key and used it to alter permissions on the LayerZero-based OFT bridge contract, minting large amounts of SFUND on Avalanche with nothing actually bridged from another chain, then dumped the fake tokens across Ethereum, Arbitrum, Base, and finally BNB Chain. | I23: https://decrypt.co/341076/north-korean-hackers-drain-1-2m-from-seedify-bridge | J23: https://crypto.news/seedifys-sfund-implodes-99-dprk-hackers-exploit-bridge-flaw/ | K23: https://games.gg/news/seedify-suffers-breach/ | L23: E2 | M23: Credential Seizure (CS) | N23: FD-5 Governance & Operations | O23: A compromised developer private key was used directly to alter bridge contract permissions and authorize unbacked minting. The credential, not the code, was the point of failure. A stolen developer credential used directly to authorize minting is Credential Seizure, and for this we have mapped it to Credential Seizure (CS). Developer and admin keys with permission altering power sit squarely in the governance and operations domain, so for this we have mapped it to FD-5 Governance & Operations. | Q23: None recorded | R23: No | U23: =IF(L23="E4","Low",IF(OR(R23="Yes",L23="E3"),"Medium","High")) -> High | X23: Real assets obtained with unbacked tokens
A24: BR-023 | B24: 45914 | C24: =YEAR(B24) -> 2025 | D24: Yala (Bitcoin-collateralized stablecoin bridge) | E24: ~$7.64 Million | F24: 7640000 | H24: A compromised temporary deployment key, not a smart-contract bug. An attacker obtained a temporary key meant for an authorized bridge deployment and used it to stand up an entirely unauthorized cross-chain bridge of their own. Through that rogue bridge, they overissued ~30 million YU tokens on Solana with nothing backing them, then drained ~7.64 million USDC (~1,636 ETH) through the withdrawal path — depegging YU to $0.20 before the team burned the illegitimate supply and injected $5.5M to restore the peg. Core protocol contracts and Bitcoin reserves were untouched; Bangkok police arrested the suspect on October 29, 2025. | I24: https://www.halborn.com/blog/post/explained-the-yala-hack-september-2025 | J24: https://www.bitget.com/news/detail/12560604970177 | K24: https://quadrigainitiative.com/casestudy/yalaprotocoldormantoftuunauthorizedmintandbridge.php | L24: E2 | M24: Credential Seizure (CS) | N24: FD-5 Governance & Operations | O24: A compromised temporary deployment key gave the attacker the same standing as an authorized deployer, letting them stand up and operate their own unauthorized bridge instance. A stolen deployment credential used to gain standing equivalent to an authorized operator is Credential Seizure, and for this we have mapped it to Credential Seizure (CS). Deployment and admin credentials are part of the bridge's operational control plane, so for this we have mapped it to FD-5 Governance & Operations. | Q24: None recorded | R24: No | U24: =IF(L24="E4","Low",IF(OR(R24="Yes",L24="E3"),"Medium","High")) -> High | X24: Bridge-held assets withdrawn
A25: BR-024 | B25: 45909 | C25: =YEAR(B25) -> 2025 | D25: Shibarium Bridge | E25: $2.4 Million | F25: 2400000 | H25: Signature Manipulation: Combined flash-loan and manipulated validator signatures to bypass proper collateralization. A flash-loan-powered validator takeover. Shibarium's bridge needed a two-thirds validator majority (8 of 12) to approve state checkpoints. The attacker flash-borrowed 4.6 million BONE tokens, delegated them to a compromised validator, and briefly pushed their controlled stake past the two-thirds threshold — enough to sign a fraudulent checkpoint and authorize a bogus bridge withdrawal of ETH and SHIB, all within a single block, repaying the flash loan with the stolen funds. | I25: https://news.shib.io/2025/09/22/shibarium-bridge-exploit-kaal-drops-latest-dev-report-post-hack/ | J25: https://www.theblock.co/post/370536/shibarium-bridge-suffers-sophisticated-flash-loan-attack-with-2-4-million-drained | K25: https://cryptonews.com/news/shibarium-reboots-after-4m-hack-pledges-user-refunds-heres-the-plan/ | L25: E1 | M25: Economic-State Manipulation (ESM) | N25: FD-4 Execution | O25: The attacker used flash-loaned BONE to temporarily inflate delegated stake past the two-thirds validator signing threshold within one block, pushed through a fraudulent checkpoint and withdrawal, and repaid the loan from the proceeds. The object being manipulated is the bridge's economic security state, the stake distribution that decides who may sign checkpoints; the flash loan only supplied the temporary capital. Distorting the economic state that a bridge's authorization depends on, and extracting value from that distortion, is the Economic-State Manipulation pattern, and for this we have mapped it to Economic-State Manipulation (ESM). The manipulated stake threshold directly gates the function that executes the withdrawal, so for this we have mapped it to FD-4 Execution. | Q25: Flash loan; compromised validator | R25: Yes | S25: Credential Seizure (CS) | T25: FD-5 Governance & Operations | U25: =IF(L25="E4","Low",IF(OR(R25="Yes",L25="E3"),"Medium","High")) -> Medium | X25: Bridge-held assets withdrawn
A26: BR-025 | B26: 45847 | C26: =YEAR(B26) -> 2025 | D26: ZKSwap Ethereum Bridge | E26: $5 million | F26: 5000000 | H26: A broken proof-verification function. ZKSwap's emergency "Exodus Mode" (meant to let users self-withdraw if operators go offline) relied on a verifyExitProof() function that always returned true instead of actually checking the cryptographic proof. The attacker submitted completely fabricated withdrawal proofs, which were accepted as genuine, then exploited weak duplicate-claim logic to repeat the trick across multiple token balances before withdrawing. | I26: https://www.blockaid.io/blog/how-zkswaps-5m-exploit-couldve-been-prevented-with-onchain-monitoring | J26: https://blog.verichains.io/p/audit-the-deployment-not-just-the | K26: https://quadrigainitiative.com/casestudy/zkswapexodusmodeflawenabledfakeproofwithdrawals.php | L26: E2 | M26: Proof Forgery (PF) | N26: FD-3 Verification | O26: verifyExitProof() was hardcoded to always return true instead of actually checking the submitted cryptographic proof, so completely fabricated withdrawal proofs passed verification. A proof-verification function that accepts fabricated proofs is the defining case of Proof Forgery, and for this we have mapped it to Proof Forgery (PF). verifyExitProof() is, by name and function, the bridge's proof verification checkpoint, so for this we have mapped it to FD-3 Verification. | Q26: None recorded | R26: No | U26: =IF(L26="E4","Low",IF(OR(R26="Yes",L26="E3"),"Medium","High")) -> High | X26: Bridge-held assets withdrawn
A27: BR-026 | B27: 45840 | C27: =YEAR(B27) -> 2025 | D27: Router Protocol | E27: $1.1 million | F27: 1100000 | H27: A logic flaw in Router Chain's custom cross-chain messaging module. The system failed to check that RequestSender == TxSender, letting the attacker spoof the sender field on an outbound request. The bridge's orchestrators unknowingly signed the forged request, and the Ethereum-side gateway contract released funds trusting that spoofed sender field. | I27: https://routerprotocol.medium.com/incident-report-router-protocol-asset-bridge-exploit-and-response-833f5bb95a31 | L27: E3 | M27: Logic Exploitation (LE) | N27: FD-2 Relay | O27: The bug is a missing equality check between RequestSender and TxSender in Router Chain's own messaging code, a straightforward coding omission that let a spoofed field slip through untouched logic. A plain missing-check coding defect, rather than a cryptographic or event-level forgery, is the Logic Exploitation pattern, and for this we have mapped it to Logic Exploitation (LE). The flaw sits inside the cross-chain messaging and orchestration module that relays and attests requests between chains, so for this we have mapped it to FD-2 Relay rather than FD-1 Deposit or FD-4 Execution. | P27: Single official source (project incident report); satisfies the official post-mortem rule. | Q27: None recorded | R27: No | U27: =IF(L27="E4","Low",IF(OR(R27="Yes",L27="E3"),"Medium","High")) -> Medium | X27: Bridge-held assets withdrawn
A28: BR-027 | B28: 45809 | C28: =YEAR(B28) -> 2025 | D28: Force Bridge | E28: $3.76 Million | F28: 3760000 | H28: Access Control: Compromised private keys allowed unauthorized access to critical token swap and withdrawal functions. A supply chain attack, not a smart contract bug. Attackers slipped malicious code into a Docker image deployed to validator nodes during an April system upgrade, which secretly exfiltrated validator private keys over encrypted channels. Weeks later, they used those stolen keys to push through fraudulent "unlock" transactions on Ethereum and BNB Chain, draining ETH, USDT, USDC, DAI, and WBTC | I28: https://talk.nervos.org/t/force-bridge-incident-root-cause-analysis-user-commitment/8801 | J28: https://thedefiant.io/news/hacks/nervos-networks-force-bridge-cross-chain-hack-exploits-access-control-steals-3-9-26adcaf3 | K28: https://talk.nervos.org/t/force-bridge-user-compensation-plan-announcement/8810 | L28: E1 | M28: Infrastructure Hijacking (IH) | N28: FD-5 Governance & Operations | O28: The attacker's entry point was the CI/CD deployment pipeline itself, malicious code was slipped into a Docker image pushed to validator nodes during a routine system upgrade, and that code exfiltrated validator private keys as a side effect. Compromising the software supply chain and build pipeline to inject malicious capability, rather than directly targeting an individual's key through phishing, is the Infrastructure Hijacking pattern, and for this we have mapped it to Infrastructure Hijacking (IH). CI/CD pipelines and deployment infrastructure are explicitly part of the supporting off-chain infrastructure this domain covers, so for this we have mapped it to FD-5 Governance & Operations. | Q28: Validator key exfiltration | R28: Yes | S28: Credential Seizure (CS) | T28: FD-5 Governance & Operations | U28: =IF(L28="E4","Low",IF(OR(R28="Yes",L28="E3"),"Medium","High")) -> Medium | X28: Bridge-held assets withdrawn
A29: BR-028 | B29: 45655 | C29: =YEAR(B29) -> 2024 | D29: FEG Token Bridge (SmartBridge) | E29: $1.3 Million | F29: 1300000 | H29: FEG's SmartBridge relies on Wormhole to carry cross-chain messages, and only its relayer contract is allowed to register a withdrawal in SmartBridge. That relayer maintains a whitelist of source addresses but lets the whitelist itself be updated via an incoming bridged message, and never checks whether the message doing the updating was actually authorized to do so. The attacker crafted a malicious Wormhole message on one chain that added their own contract to the whitelist, then sent a second message invoking registerWithdraw to credit themselves a withdrawable FEG balance with no matching deposit. The same three-step exploit was repeated across Ethereum, Base, and BSC for a combined ~$1.3M, and the proceeds were swapped to ETH/BNB and sent to Tornado Cash. | I29: https://www.certik.com/blog/feg-bridge-exploit-technical-analysis | J29: https://www.halborn.com/blog/post/explained-the-feed-every-gorilla-feg-hack-december-2024 | L29: E2 | M29: Event Injection (EI) | N29: FD-2 Relay | O29: The FEG Relayer contract received an incoming Wormhole message and registered a withdrawal without ever checking whether the message's source address was actually authorized to trigger that registration, so a malicious message from an unrelated address was processed as if it were a genuine bridge instruction. Accepting a message whose source was never validated as a real, authorized bridge action is the event source validation failure that defines Event Injection, and for this we have mapped it to Event Injection (EI). The missing check lived specifically inside the relayer contract's own message handling code, not in how deposits are emitted on the source chain, so for this we have mapped it to FD-2 Relay. | Q29: None recorded | R29: No | U29: =IF(L29="E4","Low",IF(OR(R29="Yes",L29="E3"),"Medium","High")) -> High | X29: Bridge-held assets withdrawn
A30: BR-029 | B30: 45510 | C30: =YEAR(B30) -> 2024 | D30: Ronin Bridge (2nd incident) | E30: $12 Million | F30: 12000000 | H30: Ronin's team upgraded its bridge manager from V2 to V4 and deployed a new MainchainGatewayV3 implementation, but never called the required initializeV3 function. That left the newly introduced _totalOperatorWeight storage variable at its zero default, which silently disabled the minimumVoteWeight check, the safeguard meant to confirm that enough validator weight had signed off before a withdrawal could execute. 48 minutes after the upgrade, an MEV bot spotted that any withdrawal request would now pass this check regardless of signer weight and withdrew 4,000 ETH and $2M USDC; a pre-existing daily withdrawal cap prevented a further ~$72M from being taken, and the funds were returned within hours. | I30: https://blog.solidityscan.com/ronin-bridge-hack-analysis-d8f64b8fe683/ | J30: https://www.beosin.com/resources/the-root-cause-of-ronin-bridges-abnormal-activities | L30: E2 | M30: Logic Exploitation (LE) | N30: FD-3 Verification | O30: The team's contract upgrade never called initializeV3, leaving the _totalOperatorWeight variable at its zero default, so the minimumVoteWeight check silently accepted any withdrawal regardless of how much validator weight actually signed it. The contract executed exactly as coded, it simply never enforced the safeguard it was supposed to, which is the Logic Exploitation pattern, and for this we have mapped it to Logic Exploitation (LE). The disabled minimumVoteWeight parameter is specifically the multi-signature consensus check that is meant to confirm sufficient validator weight approved a withdrawal before it is authorized, so for this we have mapped it to FD-3 Verification. | Q30: None recorded | R30: No | U30: =IF(L30="E4","Low",IF(OR(R30="Yes",L30="E3"),"Medium","High")) -> High | X30: Bridge-held assets withdrawn
A31: BR-030 | B31: 45489 | C31: =YEAR(B31) -> 2024 | D31: Li.Fi (bridge / DEX aggregator) | E31: ~$11.6 Million | F31: 11600000 | H31: Five days before the attack, LI.FI deployed a new GasZipFacet contract to enable gas refueling during bridging. Its depositToGasZipERC20 function passed a user-supplied _swapData argument straight into LibSwap.swap(), which executes a low-level call using whatever target address and call data it's given. Every other facet in LI.FI's Diamond contract checked that call target against a whitelist of approved DEXs and contracts before executing it, but GasZipFacet was missing that check. The attacker crafted a swapData payload that called transferFrom instead of a genuine swap, draining USDC, USDT, and DAI from any of the 153 wallets on Ethereum and Arbitrum that had granted the LI.FI contract an infinite approval. | I31: https://li.fi/knowledge-hub/incident-report-16th-july | J31: https://blocksec.com/blog/illicit-fund-flow-case-study-lifi-attack-metasleuth | L31: E1 | M31: Logic Exploitation (LE) | N31: FD-4 Execution | O31: The newly deployed GasZipFacet contract passed attacker-controlled call data straight into LibSwap.swap() without checking it against the whitelist of approved contracts and functions that every other facet enforced, letting the attacker substitute a transferFrom call for a swap. A missing whitelist check in the contract's own call-execution logic, rather than any forged message or stolen key, is the Logic Exploitation pattern, and for this we have mapped it to Logic Exploitation (LE). The unchecked call sits inside the function that actually executes the token movement against approved wallets, so for this we have mapped it to FD-4 Execution. | P31: Included: exploited GasZipFacet is the aggregator's cross-chain gas-refuel (bridging) facet. | Q31: None recorded | R31: No | U31: =IF(L31="E4","Low",IF(OR(R31="Yes",L31="E3"),"Medium","High")) -> High | X31: Wallet funds drained (approvals or redirection)
A32: BR-031 | B32: 45426 | C32: =YEAR(B32) -> 2024 | D32: ALEX Lab (XLink Bridge) | E32: $4.3 Million | F32: 4300000 | H32: CertiK traced the incident to a phishing attack that compromised the private key of ALEX's XLink bridge deployer account. Using that key, the attacker pushed several unauthorized proxy upgrades to the Bridge Endpoint contract on BNB Smart Chain and to the corresponding contract on the Stacks/Bitcoin side, redirecting the bridge's withdrawal logic to a malicious implementation they controlled. The attacker withdrew BTC, USDC, and Sugar Kingdom (SKO) tokens, and attempted a larger withdrawal on BNB Chain, but a bug in their own malicious implementation let a white-hat front-run and secure part of the funds; ALEX later recovered a large share of the total through a 10% bounty negotiation. | I32: https://cryptoslate.com/bitcoin-defi-app-alex-lab-links-4-million-exploit-to-lazarus-group/ | J32: https://www.certik.com/blog/alex | K32: https://www.coindesk.com/business/2024/05/15/bitcoin-defi-tool-alex-lab-loses-43m-in-hack-offers-10-bounty-for-stolen-funds | L32: E2 | M32: Credential Seizure (CS) | N32: FD-5 Governance & Operations | O32: A phishing attack compromised the deployer's private key, and the attacker used that key directly to push several unauthorized proxy upgrades to the Bridge Endpoint contract, redirecting withdrawals to themselves with no code vulnerability involved. Using a genuinely stolen credential to authorize the action directly is the Credential Seizure pattern, and for this we have mapped it to Credential Seizure (CS). A deployer key with upgrade authority over the bridge contract is a persistent administrative credential, so for this we have mapped it to FD-5 Governance & Operations. | Q32: Phishing | R32: No | U32: =IF(L32="E4","Low",IF(OR(R32="Yes",L32="E3"),"Medium","High")) -> High | X32: Bridge-held assets withdrawn
A33: BR-032 | B33: 45408 | C33: =YEAR(B33) -> 2024 | D33: Pike Finance (1st incident) | E33: ~$299K | F33: 299000 | H33: Pike integrated Circle's CCTP (via Gelato automation) to let users mint USDC directly on a destination chain after burning it on a source chain, but responsibility for validating the receiver address and transfer amount inside each incoming CCTP message was left to Pike's own contract rather than Circle's or Gelato's infrastructure. That validation was missing, so the attacker submitted a forged CCTP message with a manipulated recipient address and amount, which Pike's USDC pool accepted as a legitimate mint instruction and paid out against, draining ~$299K across Ethereum, Arbitrum, and Optimism. | I33: https://mirror.xyz/pikefinance.eth/klLV4rRqNYxjRQp0NAfVLboLYtX98P9iYOOf06FUapg | J33: https://www.certik.com/blog/pike-finance-incident-analysis | L33: E1 | M33: Proof Forgery (PF) | N33: FD-3 Verification | O33: Pike's own integration was responsible for validating the receiver address and amount inside an incoming CCTP cross-chain message before honoring it, and that validation was missing, so the attacker submitted a forged message with a manipulated recipient and amount that Pike accepted as a legitimate mint instruction. Forging a cross-chain message that passes an inadequate verification check to obtain a fraudulent release is the Proof Forgery pattern, and for this we have mapped it to Proof Forgery (PF). The missing validation sat directly inside the step responsible for confirming that an incoming CCTP message is authentic before funds move, so for this we have mapped it to FD-3 Verification. | P33: Included: exploited component is Pike's handling of incoming Circle CCTP cross-chain messages. | Q33: None recorded | R33: No | U33: =IF(L33="E4","Low",IF(OR(R33="Yes",L33="E3"),"Medium","High")) -> High | X33: Bridge-held assets withdrawn
A34: BR-033 | B34: 45406 | C34: =YEAR(B34) -> 2024 | D34: XBridge | E34: ~$1.6 Million | F34: 1600000 | H34: XBridge lets users register a token pair via listToken, which records the caller as that token's _tokenOwner and grants them the right to deposit and withdraw the underlying baseToken as a bridge liquidity provider. The function never checked whether a pair had already been registered by someone else before letting a new caller claim ownership of the same baseToken under a different corresponding token, so the attacker waited for a real liquidity provider to list and fund a pair, then re-called listToken to overwrite themselves in as the new _tokenOwner and called withdrawTokens to drain the liquidity that the original owner had deposited, across Ethereum and BNB Chain. | I34: https://www.cryptotimes.io/2024/04/24/saitachains-xbridge-experienced-a-security-breach/ | J34: https://blog.verichains.io/p/when-the-bridge-is-the-risk | K34: https://olympix.security/biweekly-exploits/6m-stolen-alexlab-ngfs-xbridge-and-yiedl-compromised-by-key-theft-and-broken-access-controls | L34: E2 | M34: Logic Exploitation (LE) | N34: FD-4 Execution | O34: The listToken function never verified that the caller matched the existing token owner, so the attacker simply re-registered themselves as the owner of a token pair that someone else had already funded, then called withdrawTokens to drain it without ever depositing anything. A missing ownership check in the contract's own registration and withdrawal logic, run exactly as written, is the Logic Exploitation pattern, and for this we have mapped it to Logic Exploitation (LE). The flaw sits in the function that actually releases funds to whoever holds the (falsely claimed) owner role, so for this we have mapped it to FD-4 Execution. | Q34: None recorded | R34: No | U34: =IF(L34="E4","Low",IF(OR(R34="Yes",L34="E3"),"Medium","High")) -> High | X34: Bridge-held assets withdrawn
A35: BR-034 | B35: 45307 | C35: =YEAR(B35) -> 2024 | D35: Socket.tech (Bungee Bridge) | E35: $3.3 Million | F35: 3300000 | H35: Three days before the attack, Socket deployed a new route inside its SocketGateway contract. The route's performAction function had incomplete validation of its input parameters, and the attacker used that gap to invoke transfers directly against the token allowances that users had previously granted to SocketGateway, without those users signing any new transaction. 232 wallets that had left infinite approvals in place lost a combined $3.3M across USDC and several other assets before the route was disabled; Socket later recovered ~$2.3M through negotiation and covered the remaining shortfall. | I35: https://www.certik.com/blog/socket-tech-incident-analysis | J35: https://thedefiant.io/news/defi/socket-resumes-operations-after-users-lost-usd3-3m-to-exploit | L35: E2 | M35: Logic Exploitation (LE) | N35: FD-4 Execution | O35: A newly deployed route's performAction function had incomplete input validation, and the attacker used that gap to invoke transfers directly against any wallet that had granted the SocketGateway contract an unlimited token approval, with no forged message or stolen key involved. A missing input-validation check in the contract's own action-execution logic is the Logic Exploitation pattern, and for this we have mapped it to Logic Exploitation (LE). The vulnerable function is the one that actually executes the token transfer against a user's standing approval, so for this we have mapped it to FD-4 Execution. | P35: Included: exploited route sits in SocketGateway, the bridge aggregator's cross-chain routing contract. | Q35: None recorded | R35: No | U35: =IF(L35="E4","Low",IF(OR(R35="Yes",L35="E3"),"Medium","High")) -> High | X35: Wallet funds drained (approvals or redirection)
A36: BR-035 | B36: 45292 | C36: =YEAR(B36) -> 2024 | D36: Orbit Chain | E36: $81.5 Million | F36: 81500000 | H36: Orbit Bridge's Ethereum vault used a 10-signer multisig requiring a threshold of approvals to release funds. The team's own investigation found no smart-contract vulnerability or validator-key theft; instead, 7 of the 10 multisig signers were compromised in what Orbit described as a sophisticated stealth attack, later linked to Lazarus Group by on-chain forensics. Across six transactions in a roughly 33-minute window, the attacker used the compromised keys to authorize withdrawals of ETH, WBTC, USDT, USDC, and DAI, draining over half the bridge's total value locked. | I36: https://medium.com/orbit-chain/official-statement-regarding-orbit-bridge-exploit-551928f3dc52 | J36: https://quillaudits.substack.com/p/news-years-eve-with-a-big-hack-orbit | K36: https://www.coindesk.com/business/2024/01/02/orbit-chain-loses-81m-in-cross-chain-bridge-exploit | L36: E1 | M36: Credential Seizure (CS) | N36: FD-5 Governance & Operations | O36: Seven of the bridge's ten multisig signers were compromised in what the team described as a sophisticated stealth attack, and the attacker used those genuinely valid keys to authorize withdrawals the contract had no way of distinguishing from legitimate multisig activity. Using real, if illegitimately obtained, signing keys to authorize the transaction is the Credential Seizure pattern, and for this we have mapped it to Credential Seizure (CS). Multisig signer keys are part of the bridge's persistent operational control plane, so for this we have mapped it to FD-5 Governance & Operations. | Q36: None recorded | R36: No | U36: =IF(L36="E4","Low",IF(OR(R36="Yes",L36="E3"),"Medium","High")) -> High | X36: Bridge-held assets withdrawn
A37: BR-036 | B37: 45252 | C37: =YEAR(B37) -> 2023 | D37: HECO Bridge (Heco Chain / HTX) | E37: $86.8 Million (HECO Bridge only) | F37: 86800000 | G37: HECO Bridge only; HTX exchange hot-wallet losses (separate attack surface, ~$12.5–30M) excluded. Previously reported combined figure ~$113.3M. | H37: Key Compromise: The Heco Bridge operator wallet's private key was compromised, letting the attacker directly call the bridge's operator-only withdrawToken function. (HTX's centralized-exchange hot wallets were breached in the same window through a separate credential compromise; that is a different attack surface and its losses are excluded from this record.) | I37: https://archive.ph/8J9zt | J37: https://www.certik.com/blog/heco-bridge-exploit | K37: https://www.coindesk.com/tech/2023/11/22/justin-sun-confirms-htx-heco-chain-exploited-after-100m-in-suspicious-transfers | L37: E2 | M37: Credential Seizure (CS) | N37: FD-5 Governance & Operations | O37: The attacker compromised the private key controlling the Heco Bridge's operator wallet and used it to directly call the bridge's operator-only withdrawToken function. Using a genuinely stolen operator credential to authorize a withdrawal the bridge contract had no way of flagging as illegitimate is the Credential Seizure pattern, and for this we have mapped it to Credential Seizure (CS). The compromised operator key is part of the bridge's persistent administrative control plane rather than any single user transaction, so for this we have mapped it to FD-5 Governance & Operations. | Q37: None recorded | R37: No | U37: =IF(L37="E4","Low",IF(OR(R37="Yes",L37="E3"),"Medium","High")) -> High | X37: Bridge-held assets withdrawn
A38: BR-037 | B38: 45113 | C38: =YEAR(B38) -> 2023 | D38: Multichain | E38: $126 Million | F38: 126000000 | H38: Centralization Risk: Critical MPC private keys were under the sole control of the CEO; following his detention by Chinese authorities, funds drained from the Fantom, Moonriver, and Dogechain bridge deployments in a pattern consistent with compromised/uncontrolled key material. | I38: https://www.halborn.com/blog/post/explained-the-multichain-hack-july-2023 | J38: https://www.chainalysis.com/blog/multichain-exploit-july-2023/ | K38: https://onchainattack.org/document/examples/2023-07-multichain/ | L38: E2 | M38: Credential Seizure (CS) | N38: FD-5 Governance & Operations | O38: Multichain's cross-chain transfers were authorized entirely through MPC key shares held solely on infrastructure controlled by the CEO; once he was detained by Chinese authorities, the team lost access to that key material, and funds subsequently drained from the Fantom, Moonriver, and Dogechain bridge deployments in a pattern consistent with the compromised/uncontrolled keys. Using genuinely compromised signing key material to authorize transfers, rather than exploiting a governance vote or a code flaw, is the Credential Seizure pattern, and for this we have mapped it to Credential Seizure (CS) rather than Governance Manipulation, matching this incident's own classification in the source taxonomy. The MPC signing keys are part of the bridge's persistent operational control plane, so for this we have mapped it to FD-5 Governance & Operations. | Q38: None recorded | R38: No | U38: =IF(L38="E4","Low",IF(OR(R38="Yes",L38="E3"),"Medium","High")) -> High | X38: Bridge-held assets withdrawn
A39: BR-038 | B39: 45017 | C39: =YEAR(B39) -> 2023 | D39: Allbridge | E39: $0.57 Million | F39: 570000 | H39: Withdrawal Accounting Flaw: A logic error in Allbridge Core's liquidity-pool withdrawal formula let an attacker use a flash loan to push the real-stablecoin-to-internal-vUSD ratio far out of alignment on BNB Chain, then extract an outsized payout through the distorted pool. | I39: https://allbridge.medium.com/allbridge-core-updates-following-the-relaunch-9f7716eeb5da | J39: https://medium.com/coinmonks/decoding-allbridge-570k-flash-loan-exploit-quillaudits-8da8dccd729d | K39: https://forklog.com/en/allbridge-co-founder-reveals-real-losses-and-the-attack-vector-on-the-protocol/ | L39: E1 | M39: Economic-State Manipulation (ESM) | N39: FD-4 Execution | O39: The attacker used a flash loan within a single atomic transaction to push Allbridge Core's real-stablecoin-to-vUSD balance ratio on its BNB Chain pools far out of alignment, then extracted an outsized withdrawal before repaying the loan. The object being manipulated is the bridge's economic state, its pool balances and the internal accounting derived from them; the flash loan is only the capital source. Distorting the economic state a bridge relies on to price a release, and extracting value from that distortion, is the Economic-State Manipulation pattern, and for this we have mapped it to Economic-State Manipulation (ESM). The manipulated balance logic lives inside the function that actually executes pool withdrawals, so for this we have mapped it to FD-4 Execution. | Q39: Flash loan | R39: No | U39: =IF(L39="E4","Low",IF(OR(R39="Yes",L39="E3"),"Medium","High")) -> High | X39: Bridge-held assets withdrawn
A40: BR-039 | B40: 44841 | C40: =YEAR(B40) -> 2022 | D40: BNB Chain Token Hub (Binance Bridge) | E40: $566 Million | F40: 566000000 | H40: A flaw in the Cosmos IAVL Merkle range-proof verifier used by BSC Token Hub, the native bridge between BNB Beacon Chain and BNB Smart Chain. The hash function ignored an inner node's Right child whenever Left was present, so an attacker could attach arbitrary Right-side data without changing the computed root. That let them forge a valid-looking withdrawal proof for a deposit that never happened and mint 2 million BNB through the CrossChain contract's handlePackage/validateMerkleProof path. BSC validators halted the chain; most of the minted BNB was frozen before it could leave. | I40: https://www.bnbchain.org/en/blog/bnb-chain-ecosystem-update | J40: https://www.halborn.com/blog/post/explained-the-bnb-chain-hack-october-2022 | K40: https://www.sharkteam.org/report/analysis/20221009001A_en.pdf | L40: E1 | M40: Proof Forgery (PF) | N40: FD-3 Verification | O40: The attacker submitted a forged IAVL range proof that the destination-side verifier accepted as a genuine Beacon Chain withdrawal, minting 2 million BNB with no matching deposit. A flaw in proof-verification logic that lets an unauthorized value pass as valid is Proof Forgery, and for this we have mapped it to Proof Forgery (PF). validateMerkleProof is the Token Hub's cryptographic check that a claimed cross-chain package is authentic, so for this we have mapped it to FD-3 Verification. | Q40: None recorded | R40: No | U40: =IF(L40="E4","Low",IF(OR(R40="Yes",L40="E3"),"Medium","High")) -> High | X40: Value of unbacked minted assets
A41: BR-040 | B41: 44790 | C41: =YEAR(B41) -> 2022 | D41: Celer cBridge | E41: $0.24 Million | F41: 235000 | G41: Reported range ~$235–240K; conservative lower bound used. | H41: Not a smart-contract or protocol bug. Attackers BGP-hijacked the Amazon-hosted cbridge-prod2.celer.network prefix for about three hours, obtained a valid TLS certificate, and served a phishing frontend that pointed users at malicious lookalike contracts. Those contracts proxied most calls to the real cBridge while draining token approvals. About 32 users lost ~$235K–$240K; locked bridge liquidity was never touched. Celer initially called it DNS hijacking, then SlowMist and Coinbase confirmed BGP route hijacking of the underlying IP prefix. | I41: https://www.coinbase.com/blog/celer-bridge-incident-analysis | J41: https://medium.com/coinmonks/truth-behind-the-celer-network-cbridge-cross-chain-bridge-incident-bgp-hijacking-52556227e940 | K41: https://cryptoslate.com/celer-network-cbridge-resumes-operation-after-suffering-dns-exploit/ | L41: E2 | M41: Infrastructure Hijacking (IH) | N41: FD-5 Governance & Operations | O41: The attacker hijacked Internet routing (BGP) for Celer's frontend hostname and served a fake interface that drained user approvals, without touching the bridge contracts or any validator key. Compromising the off-chain operating environment around the bridge, DNS/routing and hosting, is the Infrastructure Hijacking pattern, and for this we have mapped it to Infrastructure Hijacking (IH). Frontend hosting, DNS, and BGP routing are supporting off-chain infrastructure in the persistent control plane, so for this we have mapped it to FD-5 Governance & Operations. | P41: Included: bridge operator's own frontend/routing infrastructure; bridge contracts and liquidity unaffected. | Q41: None recorded | R41: No | U41: =IF(L41="E4","Low",IF(OR(R41="Yes",L41="E3"),"Medium","High")) -> High | X41: Wallet funds drained (approvals or redirection)
A42: BR-041 | B42: 44774 | C42: =YEAR(B42) -> 2022 | D42: Nomad Bridge | E42: $190 Million | F42: 190000000 | H42: A June 21, 2022 Replica upgrade changed how process() looks up a message's Merkle root. Unproven messages default to root 0x00, and Replica had been initialized with committedRoot = 0x00, which set confirmAt[bytes32(0)] = 1. That made acceptableRoot(0x00) always return true, so any never-before-processed message skipped proof verification. Once the first exploit transaction was public, hundreds of copy-paste attackers drained the Ethereum/Moonbeam/Evmos bridge in an open free-for-all. Roughly a fifth of funds were later returned by whitehats. | I42: https://medium.com/nomad-xyz-blog/nomad-bridge-hack-root-cause-analysis-875ad2e5aacd | J42: https://www.certik.com/blog/nomad-bridge-exploit-incident-analysis | K42: https://www.halborn.com/blog/post/the-nomad-bridge-hack-a-deeper-dive | L42: E1 | M42: Logic Exploitation (LE) | N42: FD-3 Verification | O42: No proof was forged. A contract-initialization and upgrade bug set the trusted root to 0x00, the same default used for unproven messages, so process() treated every fresh message as already verified and executed it exactly as coded. A structural initialization flaw exploited by using the contract as written is the Logic Exploitation pattern, and for this we have mapped it to Logic Exploitation (LE). The broken check is acceptableRoot inside the message-authentication path that is supposed to confirm a root before funds move, so for this we have mapped it to FD-3 Verification. | Q42: None recorded | R42: Yes | S42: Proof Forgery (PF) | T42: FD-3 Verification | U42: =IF(L42="E4","Low",IF(OR(R42="Yes",L42="E3"),"Medium","High")) -> Medium | X42: Bridge-held assets withdrawn
A43: BR-042 | B43: 44735 | C43: =YEAR(B43) -> 2022 | D43: Horizon (Harmony) | E43: $100 Million | F43: 100000000 | H43: The Horizon Ethereum bridge used a 2-of-5 (effectively 2-of-4 live) validator multisig. Attackers compromised at least two encrypted validator private keys through a coordinated campaign against Harmony's internal infrastructure, including trojan-horse software and a subgraph-package leak that exposed private-cloud server addresses. Starting 11:06 UTC on June 23 they authorized withdrawals of 14 bridged assets on Ethereum and BNB Chain, about $100M. Harmony found no smart-contract bug. The FBI later attributed the theft to Lazarus Group (APT38). | I43: https://medium.com/harmony-one/summary-of-the-harmony-horizon-bridge-incident-f9bd87c0c68e | J43: https://www.fbi.gov/news/press-releases/fbi-confirms-lazarus-group-cyber-actors-responsible-for-harmonys-horizon-bridge-currency-theft | K43: https://medium.com/harmony-one/harmonys-horizon-bridge-hack-1e8d283b6d66 | L43: E1 | M43: Credential Seizure (CS) | N43: FD-5 Governance & Operations | O43: The attacker obtained enough genuine validator private keys to meet the 2-of-5 signing threshold and authorized withdrawals the bridge contract had no way of distinguishing from legitimate multisig activity. Using stolen signing credentials rather than a code flaw is the Credential Seizure pattern, and for this we have mapped it to Credential Seizure (CS). Validator keys are part of the bridge's persistent operational control plane, so for this we have mapped it to FD-5 Governance & Operations. | Q43: Malware (trojan) | R43: No | U43: =IF(L43="E4","Low",IF(OR(R43="Yes",L43="E3"),"Medium","High")) -> High | X43: Bridge-held assets withdrawn
A44: BR-043 | B44: 44643 | C44: =YEAR(B44) -> 2022 | D44: Ronin Network | E44: $625 Million | F44: 625000000 | H44: Sky Mavis's Ronin bridge required 5 of 9 validator signatures to approve a withdrawal. The attacker obtained four Sky Mavis validator keys through a compromised gas-free RPC node / social-engineering path, plus a fifth Axie DAO key that still had an allowlist left over from an earlier scaling arrangement. With quorum, they forged two withdrawal proofs and drained 173,600 ETH and 25.5M USDC on March 23. The theft went unnoticed for six days because large outflows were not monitored. The FBI attributed it to Lazarus Group; Sky Mavis and investors later made users whole. | I44: https://roninblockchain.substack.com/p/back-to-building-ronin-security-breach | J44: https://www.halborn.com/blog/post/explained-the-ronin-hack-march-2022 | K44: https://www.reuters.com/technology/blockchain-company-ronin-hit-by-615-million-crypto-heist-2022-03-29/ | L44: E1 | M44: Credential Seizure (CS) | N44: FD-5 Governance & Operations | O44: The attacker obtained 5 of 9 genuine validator private keys, enough to meet quorum, and used those real signatures to authorize fraudulent withdrawals. Using stolen signing credentials rather than exploiting a contract bug is the Credential Seizure pattern, and for this we have mapped it to Credential Seizure (CS). Validator keys are part of the bridge's persistent operational control plane, so for this we have mapped it to FD-5 Governance & Operations. | Q44: Social engineering | R44: No | U44: =IF(L44="E4","Low",IF(OR(R44="Yes",L44="E3"),"Medium","High")) -> High | X44: Bridge-held assets withdrawn
A45: BR-044 | B45: 44624 | C45: =YEAR(B45) -> 2022 | D45: EVODeFi | E45: $0.32 Million | F45: 320000 | H45: A Vercel hosting/domain-transfer bug let an attacker move EVODeFi's domain to an account they controlled without owner confirmation, then point the bridge frontend at their own destination wallet. Users interacting with the still-familiar UI sent funds to the attacker while the old bridge contract and existing approvals stayed in place. The team cut access in about 40 minutes and began refunds; locked contract liquidity was not drained via a code exploit. | I45: https://www.prnewswire.com/news-releases/a-bug-in-vercel-allowed-an-attacker-to-drain-320-000-from-evodefi-301506961.html | J45: https://coincodecap.com/evodefi-bridge-front-end-was-hacked | K45: https://www.banklesstimes.com/news/2023/01/31/crypto-platform-evodefi-loses-dollar320k-in-hack/ | L45: E2 | M45: Infrastructure Hijacking (IH) | N45: FD-5 Governance & Operations | O45: The attacker compromised the frontend hosting provider (Vercel) and seized the project's domain, then redirected users to a malicious destination wallet without exploiting the bridge contract. Hijacking off-chain hosting and domain infrastructure is the Infrastructure Hijacking pattern, and for this we have mapped it to Infrastructure Hijacking (IH). Frontend hosting and domain control sit in the supporting off-chain infrastructure of the persistent control plane, so for this we have mapped it to FD-5 Governance & Operations. | P45: Included: bridge operator's own frontend/domain infrastructure; bridge contract unaffected. | Q45: None recorded | R45: No | U45: =IF(L45="E4","Low",IF(OR(R45="Yes",L45="E3"),"Medium","High")) -> High | X45: Wallet funds drained (approvals or redirection)
A46: BR-045 | B46: 44597 | C46: =YEAR(B46) -> 2022 | D46: Meter.io (Meter Passport) | E46: $4.2 Million | F46: 4200000 | H46: Meter Passport's ERC-20 handler, a modified ChainSafe ChainBridge deposit path, assumed wrapped-native deposits (WETH/WBNB) would be burned or locked before a Deposit event was emitted. A publicly callable deposit() path skipped that check and did not verify msg.value or that the caller actually transferred the wrapped tokens. The attacker called deposit() with an arbitrary amount, obtained genuine Deposit events with no real lock, and withdrew about $4.2M–$4.4M across Ethereum, Moonriver, BSC, and Meter. Hundred Finance on Moonriver took a secondary hit from the depeg. | I46: https://medium.com/meter-io/post-mortem-report-meter-passport-12af6b50393d | J46: https://www.halborn.com/blog/post/explained-the-meter-io-hack-february-2022 | K46: https://certik.medium.com/4-3-million-lost-to-another-bridge-hack-db9b028a3c28 | L46: E1 | M46: Event Injection (EI) | N46: FD-1 Deposit | O46: The attacker used a deposit path that emitted a real Deposit event without locking or burning the corresponding wrapped-native tokens, so the relay treated a no-value action as a genuine deposit. A fabricated or unbacked deposit signal accepted as a real bridge event is the Event Injection pattern, and for this we have mapped it to Event Injection (EI). The flaw is in how the source-chain deposit function decides to emit the event that starts the bridge, so for this we have mapped it to FD-1 Deposit. | Q46: None recorded | R46: No | U46: =IF(L46="E4","Low",IF(OR(R46="Yes",L46="E3"),"Medium","High")) -> High | X46: Bridge-held assets withdrawn
A47: BR-046 | B47: 44594 | C47: =YEAR(B47) -> 2022 | D47: Wormhole | E47: $326 Million | F47: 326000000 | H47: A Solana toolchain upgrade deprecated load_instruction_at in favor of a checked variant that verifies the instructions sysvar account. Wormhole's core contract still used the unchecked path, so the attacker supplied a fake sysvar account, spoofed a Guardian signature set, and minted 120,000 wETH on Solana with no Ethereum deposit. They bridged 93,750 of those tokens back to Ethereum and withdrew the unwrapped ETH. Jump Crypto recapitalized the vault with 120,000 ETH within about 16 hours. | I47: https://wormholecrypto.medium.com/wormhole-incident-report-02-02-22-ad9b8f21eec6 | J47: https://www.certik.com/blog/wormhole-bridge-exploit-incident-analysis | K47: https://blog.chainalysis.com/reports/wormhole-hack-february-2022/ | L47: E1 | M47: Proof Forgery (PF) | N47: FD-3 Verification | O47: The attacker forged a Guardian-attested Wormhole message by bypassing Solana-side signature verification with a spoofed sysvar account, then minted 120,000 wETH with no real deposit. Forging a valid-looking proof to obtain an unbacked release is Proof Forgery, and for this we have mapped it to Proof Forgery (PF). The exploited code is the Guardian signature-verification step that is supposed to confirm a mint message is authentic, so for this we have mapped it to FD-3 Verification. | Q47: None recorded | R47: No | U47: =IF(L47="E4","Low",IF(OR(R47="Yes",L47="E3"),"Medium","High")) -> High | X47: Value of unbacked minted assets
A48: BR-047 | B48: 44588 | C48: =YEAR(B48) -> 2022 | D48: Qubit Finance (QBridge) | E48: $80 Million | F48: 80000000 | H48: QBridge's Ethereum-to-BSC deposit path reused one Deposit event for both native ETH and ERC-20 deposits. After an owner remapped the ETH resourceID to the zero address, deposit() called tokenAddress.safeTransferFrom() on address(0), which is a no-op that does not revert, then emitted a Deposit event as if ETH had been locked. The BSC handler minted ~77,162 qXETH against nothing; the attacker used that unbacked collateral to borrow about $80M from Qubit's BSC lending pools. No funds were returned. | I48: https://certik.medium.com/qubit-bridge-collapse-exploited-to-the-tune-of-80-million-a7ab9068e1a0 | J48: https://qbt.wiki/en/incident/what-happened/ | K48: https://www.certik.com/blog/cross-chain-vulnerabilities-and-bridge-exploits-in-2022 | L48: E1 | M48: Event Injection (EI) | N48: FD-1 Deposit | O48: Calling deposit() with zero ETH still emitted the same Deposit event used for a real ETH lock, because safeTransferFrom on the zero address silently succeeded. A source-chain event treated as proof of a deposit when no assets moved is the Event Injection pattern, and for this we have mapped it to Event Injection (EI). The flaw is in the deposit function that emits the event the destination side trusts, so for this we have mapped it to FD-1 Deposit. | Q48: None recorded | R48: No | U48: =IF(L48="E4","Low",IF(OR(R48="Yes",L48="E3"),"Medium","High")) -> High | X48: Real assets obtained with unbacked tokens
A49: BR-048 | B49: 44579 | C49: =YEAR(B49) -> 2022 | D49: Multichain / AnySwap (router approval flaw) | E49: $3 Million | F49: 3000000 | H49: Dedaub disclosed two bugs in AnyswapV5ERC20 and AnyswapRouter: depositWithPermit / anySwapOutUnderlyingWithPermit called token.permit() and then transferred from the victim if that call did not revert. WETH and several other wrapped tokens have no permit function, so the call is a no-op that still succeeds, and any wallet that had previously approved the router could be drained. Multichain's January 18 public warning to revoke approvals also tipped off attackers; multiple parties stole over $3M from users of WETH, PERI, OMT, WBNB, MATIC, and AVAX. About $1M was later returned by a self-described whitehat. Distinct from the July 2023 Multichain MPC-key collapse. | I49: https://medium.com/multichainorg/multichain-contract-vulnerability-post-mortem-d37bfab237c8 | J49: https://dedaub.com/blog/phantom-functions-and-the-billion-dollar-no-op/ | K49: https://www.halborn.com/blog/post/explained-the-multichain-hack-january-2022 | L49: E1 | M49: Logic Exploitation (LE) | N49: FD-4 Execution | O49: The router treated a no-op permit() on tokens that do not implement EIP-2612 as a successful approval, then executed transferFrom against existing user allowances exactly as the code was written. A missing success-check in the contract's own deposit/routing logic is the Logic Exploitation pattern, and for this we have mapped it to Logic Exploitation (LE). The vulnerable functions are the ones that actually move user tokens out of wallets that had approved the router, so for this we have mapped it to FD-4 Execution. | P49: Included: exploited AnyswapRouter is the bridge's cross-chain router. | Q49: None recorded | R49: No | U49: =IF(L49="E4","Low",IF(OR(R49="Yes",L49="E3"),"Medium","High")) -> High | X49: Wallet funds drained (approvals or redirection)

Sheet Summary
A1: Bridge-Only Dataset — Summary Statistics (all values are live formulas on the Dataset sheet)
A3: Study period | B3: Jan 2022 – Aug 2026
A4: Incidents in final dataset | B4: =COUNTA(Dataset!A2:A49) -> 48
A5: Incidents excluded | B5: =COUNTA('Excluded Incidents'!B2:B200) -> 12
A6: Total gross bridge-specific loss (USD) | B6: =SUM(Dataset!$F$2:$F$49) -> 2675630693
A7: Median gross loss per incident (USD) | B7: =MEDIAN(Dataset!$F$2:$F$49) -> 4250000
A8: Mean gross loss per incident (USD) | B8: =AVERAGE(Dataset!$F$2:$F$49) -> 55742306
A9: Earliest incident | B9: =MIN(Dataset!B2:B49) -> 44579
A10: Latest incident | B10: =MAX(Dataset!B2:B49) -> 46257
A12: Attack Pattern | B12: Incidents | C12: Share of incidents | D12: Total loss (USD) | E12: Median loss (USD)
A13: Event Injection (EI) | B13: =COUNTIFS(Dataset!$M$2:$M$49,$A13) -> 7 | C13: =IF($B$4=0,0,B13/$B$4) -> 0.14583333 | D13: =SUMIFS(Dataset!$F$2:$F$49,Dataset!$M$2:$M$49,$A13) -> 90483000 | E13: {=IF(B13=0,0,MEDIAN(IF(Dataset!$M$2:$M$49=$A13,Dataset!$F$2:$F$49)))} -> 1300000
A14: Proof Forgery (PF) | B14: =COUNTIFS(Dataset!$M$2:$M$49,$A14) -> 13 | C14: =IF($B$4=0,0,B14/$B$4) -> 0.27083333 | D14: =SUMIFS(Dataset!$F$2:$F$49,Dataset!$M$2:$M$49,$A14) -> 1233436000 | E14: {=IF(B14=0,0,MEDIAN(IF(Dataset!$M$2:$M$49=$A14,Dataset!$F$2:$F$49)))} -> 7000000
A15: Logic Exploitation (LE) | B15: =COUNTIFS(Dataset!$M$2:$M$49,$A15) -> 9 | C15: =IF($B$4=0,0,B15/$B$4) -> 0.1875 | D15: =SUMIFS(Dataset!$F$2:$F$49,Dataset!$M$2:$M$49,$A15) -> 270434000 | E15: {=IF(B15=0,0,MEDIAN(IF(Dataset!$M$2:$M$49=$A15,Dataset!$F$2:$F$49)))} -> 3300000
A16: Economic-State Manipulation (ESM) | B16: =COUNTIFS(Dataset!$M$2:$M$49,$A16) -> 3 | C16: =IF($B$4=0,0,B16/$B$4) -> 0.0625 | D16: =SUMIFS(Dataset!$F$2:$F$49,Dataset!$M$2:$M$49,$A16) -> 4620000 | E16: {=IF(B16=0,0,MEDIAN(IF(Dataset!$M$2:$M$49=$A16,Dataset!$F$2:$F$49)))} -> 1650000
A17: Credential Seizure (CS) | B17: =COUNTIFS(Dataset!$M$2:$M$49,$A17) -> 13 | C17: =IF($B$4=0,0,B17/$B$4) -> 0.27083333 | D17: =SUMIFS(Dataset!$F$2:$F$49,Dataset!$M$2:$M$49,$A17) -> 1072342693 | E17: {=IF(B17=0,0,MEDIAN(IF(Dataset!$M$2:$M$49=$A17,Dataset!$F$2:$F$49)))} -> 10700000
A18: Infrastructure Hijacking (IH) | B18: =COUNTIFS(Dataset!$M$2:$M$49,$A18) -> 3 | C18: =IF($B$4=0,0,B18/$B$4) -> 0.0625 | D18: =SUMIFS(Dataset!$F$2:$F$49,Dataset!$M$2:$M$49,$A18) -> 4315000 | E18: {=IF(B18=0,0,MEDIAN(IF(Dataset!$M$2:$M$49=$A18,Dataset!$F$2:$F$49)))} -> 320000
A19: Total | B19: =SUM(B13:B18) -> 48 | C19: =SUM(C13:C18) -> 1 | D19: =SUM(D13:D18) -> 2675630693 | F19: =IF(B19=$B$4,"OK — reconciles","CHECK — does not reconcile") -> OK — reconciles
A21: Primary Functional Domain | B21: Incidents | C21: Share of incidents | D21: Total loss (USD) | E21: Median loss (USD)
A22: FD-1 Deposit | B22: =COUNTIFS(Dataset!$N$2:$N$49,$A22) -> 5 | C22: =IF($B$4=0,0,B22/$B$4) -> 0.10416667 | D22: =SUMIFS(Dataset!$F$2:$F$49,Dataset!$N$2:$N$49,$A22) -> 84683000 | E22: {=IF(B22=0,0,MEDIAN(IF(Dataset!$N$2:$N$49=$A22,Dataset!$F$2:$F$49)))} -> 200000
A23: FD-2 Relay | B23: =COUNTIFS(Dataset!$N$2:$N$49,$A23) -> 3 | C23: =IF($B$4=0,0,B23/$B$4) -> 0.0625 | D23: =SUMIFS(Dataset!$F$2:$F$49,Dataset!$N$2:$N$49,$A23) -> 6900000 | E23: {=IF(B23=0,0,MEDIAN(IF(Dataset!$N$2:$N$49=$A23,Dataset!$F$2:$F$49)))} -> 1300000
A24: FD-3 Verification | B24: =COUNTIFS(Dataset!$N$2:$N$49,$A24) -> 15 | C24: =IF($B$4=0,0,B24/$B$4) -> 0.3125 | D24: =SUMIFS(Dataset!$F$2:$F$49,Dataset!$N$2:$N$49,$A24) -> 1435436000 | E24: {=IF(B24=0,0,MEDIAN(IF(Dataset!$N$2:$N$49=$A24,Dataset!$F$2:$F$49)))} -> 7540000
A25: FD-4 Execution | B25: =COUNTIFS(Dataset!$N$2:$N$49,$A25) -> 9 | C25: =IF($B$4=0,0,B25/$B$4) -> 0.1875 | D25: =SUMIFS(Dataset!$F$2:$F$49,Dataset!$N$2:$N$49,$A25) -> 71954000 | E25: {=IF(B25=0,0,MEDIAN(IF(Dataset!$N$2:$N$49=$A25,Dataset!$F$2:$F$49)))} -> 2400000
A26: FD-5 Governance & Operations | B26: =COUNTIFS(Dataset!$N$2:$N$49,$A26) -> 16 | C26: =IF($B$4=0,0,B26/$B$4) -> 0.33333333 | D26: =SUMIFS(Dataset!$F$2:$F$49,Dataset!$N$2:$N$49,$A26) -> 1076657693 | E26: {=IF(B26=0,0,MEDIAN(IF(Dataset!$N$2:$N$49=$A26,Dataset!$F$2:$F$49)))} -> 5970000
A27: Total | B27: =SUM(B22:B26) -> 48 | C27: =SUM(C22:C26) -> 1 | D27: =SUM(D22:D26) -> 2675630693 | F27: =IF(B27=$B$4,"OK — reconciles","CHECK — does not reconcile") -> OK — reconciles
A29: Year | B29: Incidents | C29: Share of incidents | D29: Total loss (USD) | E29: Median loss (USD)
A30: 2022 | B30: =COUNTIFS(Dataset!$C$2:$C$49,$A30) -> 10 | C30: =IF($B$4=0,0,B30/$B$4) -> 0.20833333 | D30: =SUMIFS(Dataset!$F$2:$F$49,Dataset!$C$2:$C$49,$A30) -> 1894755000 | E30: {=IF(B30=0,0,MEDIAN(IF(Dataset!$C$2:$C$49=$A30,Dataset!$F$2:$F$49)))} -> 90000000
A31: 2023 | B31: =COUNTIFS(Dataset!$C$2:$C$49,$A31) -> 3 | C31: =IF($B$4=0,0,B31/$B$4) -> 0.0625 | D31: =SUMIFS(Dataset!$F$2:$F$49,Dataset!$C$2:$C$49,$A31) -> 213370000 | E31: {=IF(B31=0,0,MEDIAN(IF(Dataset!$C$2:$C$49=$A31,Dataset!$F$2:$F$49)))} -> 86800000
A32: 2024 | B32: =COUNTIFS(Dataset!$C$2:$C$49,$A32) -> 8 | C32: =IF($B$4=0,0,B32/$B$4) -> 0.16666667 | D32: =SUMIFS(Dataset!$F$2:$F$49,Dataset!$C$2:$C$49,$A32) -> 115899000 | E32: {=IF(B32=0,0,MEDIAN(IF(Dataset!$C$2:$C$49=$A32,Dataset!$F$2:$F$49)))} -> 3800000
A33: 2025 | B33: =COUNTIFS(Dataset!$C$2:$C$49,$A33) -> 8 | C33: =IF($B$4=0,0,B33/$B$4) -> 0.16666667 | D33: =SUMIFS(Dataset!$F$2:$F$49,Dataset!$C$2:$C$49,$A33) -> 24117693 | E33: {=IF(B33=0,0,MEDIAN(IF(Dataset!$C$2:$C$49=$A33,Dataset!$F$2:$F$49)))} -> 2700000
A34: 2026 | B34: =COUNTIFS(Dataset!$C$2:$C$49,$A34) -> 19 | C34: =IF($B$4=0,0,B34/$B$4) -> 0.39583333 | D34: =SUMIFS(Dataset!$F$2:$F$49,Dataset!$C$2:$C$49,$A34) -> 427489000 | E34: {=IF(B34=0,0,MEDIAN(IF(Dataset!$C$2:$C$49=$A34,Dataset!$F$2:$F$49)))} -> 4300000
A35: Total | B35: =SUM(B30:B34) -> 48 | C35: =SUM(C30:C34) -> 1 | D35: =SUM(D30:D34) -> 2675630693 | F35: =IF(B35=$B$4,"OK — reconciles","CHECK — does not reconcile") -> OK — reconciles
A37: Evidence Level | B37: Incidents | C37: Share of incidents | D37: Total loss (USD)
A38: E1 | B38: =COUNTIFS(Dataset!$L$2:$L$49,$A38) -> 21 | C38: =IF($B$4=0,0,B38/$B$4) -> 0.4375 | D38: =SUMIFS(Dataset!$F$2:$F$49,Dataset!$L$2:$L$49,$A38) -> 2316726000
A39: E2 | B39: =COUNTIFS(Dataset!$L$2:$L$49,$A39) -> 23 | C39: =IF($B$4=0,0,B39/$B$4) -> 0.47916667 | D39: =SUMIFS(Dataset!$F$2:$F$49,Dataset!$L$2:$L$49,$A39) -> 305269693
A40: E3 | B40: =COUNTIFS(Dataset!$L$2:$L$49,$A40) -> 3 | C40: =IF($B$4=0,0,B40/$B$4) -> 0.0625 | D40: =SUMIFS(Dataset!$F$2:$F$49,Dataset!$L$2:$L$49,$A40) -> 52900000
A41: E4 | B41: =COUNTIFS(Dataset!$L$2:$L$49,$A41) -> 1 | C41: =IF($B$4=0,0,B41/$B$4) -> 0.020833333 | D41: =SUMIFS(Dataset!$F$2:$F$49,Dataset!$L$2:$L$49,$A41) -> 735000
A42: Total | B42: =SUM(B38:B41) -> 48 | C42: =SUM(C38:C41) -> 1 | D42: =SUM(D38:D41) -> 2675630693 | F42: =IF(B42=$B$4,"OK — reconciles","CHECK — does not reconcile") -> OK — reconciles
A44: Note: losses are gross bridge-specific losses (Dataset column F): value taken at the time of the incident, recoveries not subtracted (see Loss Normalization Note and Codebook). Median columns are array formulas.
A46: Classification quality | B46: Value
A47: Boundary cases | B47: =COUNTIF(Dataset!$R$2:$R$49,"Yes") -> 6
A48: Classification confidence: High | B48: =COUNTIF(Dataset!$U$2:$U$49,"High") -> 38
A49: Classification confidence: Medium | B49: =COUNTIF(Dataset!$U$2:$U$49,"Medium") -> 9
A50: Classification confidence: Low | B50: =COUNTIF(Dataset!$U$2:$U$49,"Low") -> 1
A51: Incidents involving a flash loan | B51: =COUNTIF(Dataset!$Q$2:$Q$49,"*Flash loan*") -> 4
A53: Loss concentration | B53: Value
A54: Largest incident share of total loss | B54: =MAX(Dataset!$F$2:$F$49)/$B$6 -> 0.23358979
A55: Five largest incidents share | B55: =(LARGE(Dataset!$F$2:$F$49,1)+LARGE(Dataset!$F$2:$F$49,2)+LARGE(Dataset!$F$2:$F$49,3)+LARGE(Dataset!$F$2:$F$49,4)+LARGE(Dataset!$F$2:$F$49,5))/$B$6 -> 0.74711357
A56: Ten largest incidents share | B56: =(LARGE(Dataset!$F$2:$F$49,1)+LARGE(Dataset!$F$2:$F$49,2)+LARGE(Dataset!$F$2:$F$49,3)+LARGE(Dataset!$F$2:$F$49,4)+LARGE(Dataset!$F$2:$F$49,5)+LARGE(Dataset!$F$2:$F$49,6)+LARGE(Dataset!$F$2:$F$49,7)+LARGE(Dataset!$F$2:$F$49,8)+LARGE(Dataset!$F$2:$F$49,9)+LARGE(Dataset!$F$2:$F$49,10))/$B$6 -> 0.92438019
A57: Gini coefficient (incident-level gross loss) | B57: {=SUMPRODUCT(ABS(Dataset!$F$2:$F$49-TRANSPOSE(Dataset!$F$2:$F$49)))/(2*COUNT(Dataset!$F$2:$F$49)^2*AVERAGE(Dataset!$F$2:$F$49))} -> 0.83261767
A59: Inter-rater agreement (fill Dataset columns V and W) | B59: Attack pattern | C59: Functional domain
A60: Incidents coded by second coder | B60: =COUNTA(Dataset!$V$2:$V$49) -> 0 | C60: =COUNTA(Dataset!$W$2:$W$49) -> 0
A61: Raw agreement | B61: =IF(B60=0,"Awaiting second coder",SUMPRODUCT((Dataset!$M$2:$M$49=Dataset!$V$2:$V$49)*(Dataset!$V$2:$V$49<>""))/B60) -> Awaiting second coder | C61: =IF(C60=0,"Awaiting second coder",SUMPRODUCT((Dataset!$N$2:$N$49=Dataset!$W$2:$W$49)*(Dataset!$W$2:$W$49<>""))/C60) -> Awaiting second coder
A62: Expected chance agreement | B62: =IF(B60=0,"",SUMPRODUCT(C66:C71,D66:D71)/B60^2) | C62: =IF(C60=0,"",SUMPRODUCT(C74:C78,D74:D78)/C60^2)
A63: Cohen's kappa | B63: =IF(B60=0,"Awaiting second coder",(B61-B62)/(1-B62)) -> Awaiting second coder | C63: =IF(C60=0,"Awaiting second coder",(C61-C62)/(1-C62)) -> Awaiting second coder
A65: Kappa helper: attack pattern | C65: Coder 1 (on rows coded by coder 2) | D65: Coder 2
A66: =A13 -> Event Injection (EI) | C66: =COUNTIFS(Dataset!$M$2:$M$49,$A66,Dataset!$V$2:$V$49,"<>") -> 0 | D66: =COUNTIF(Dataset!$V$2:$V$49,$A66) -> 0
A67: =A14 -> Proof Forgery (PF) | C67: =COUNTIFS(Dataset!$M$2:$M$49,$A67,Dataset!$V$2:$V$49,"<>") -> 0 | D67: =COUNTIF(Dataset!$V$2:$V$49,$A67) -> 0
A68: =A15 -> Logic Exploitation (LE) | C68: =COUNTIFS(Dataset!$M$2:$M$49,$A68,Dataset!$V$2:$V$49,"<>") -> 0 | D68: =COUNTIF(Dataset!$V$2:$V$49,$A68) -> 0
A69: =A16 -> Economic-State Manipulation (ESM) | C69: =COUNTIFS(Dataset!$M$2:$M$49,$A69,Dataset!$V$2:$V$49,"<>") -> 0 | D69: =COUNTIF(Dataset!$V$2:$V$49,$A69) -> 0
A70: =A17 -> Credential Seizure (CS) | C70: =COUNTIFS(Dataset!$M$2:$M$49,$A70,Dataset!$V$2:$V$49,"<>") -> 0 | D70: =COUNTIF(Dataset!$V$2:$V$49,$A70) -> 0
A71: =A18 -> Infrastructure Hijacking (IH) | C71: =COUNTIFS(Dataset!$M$2:$M$49,$A71,Dataset!$V$2:$V$49,"<>") -> 0 | D71: =COUNTIF(Dataset!$V$2:$V$49,$A71) -> 0
A73: Kappa helper: functional domain | C73: Coder 1 (on rows coded by coder 2) | D73: Coder 2
A74: =A22 -> FD-1 Deposit | C74: =COUNTIFS(Dataset!$N$2:$N$49,$A74,Dataset!$W$2:$W$49,"<>") -> 0 | D74: =COUNTIF(Dataset!$W$2:$W$49,$A74) -> 0
A75: =A23 -> FD-2 Relay | C75: =COUNTIFS(Dataset!$N$2:$N$49,$A75,Dataset!$W$2:$W$49,"<>") -> 0 | D75: =COUNTIF(Dataset!$W$2:$W$49,$A75) -> 0
A76: =A24 -> FD-3 Verification | C76: =COUNTIFS(Dataset!$N$2:$N$49,$A76,Dataset!$W$2:$W$49,"<>") -> 0 | D76: =COUNTIF(Dataset!$W$2:$W$49,$A76) -> 0
A77: =A25 -> FD-4 Execution | C77: =COUNTIFS(Dataset!$N$2:$N$49,$A77,Dataset!$W$2:$W$49,"<>") -> 0 | D77: =COUNTIF(Dataset!$W$2:$W$49,$A77) -> 0
A78: =A26 -> FD-5 Governance & Operations | C78: =COUNTIFS(Dataset!$N$2:$N$49,$A78,Dataset!$W$2:$W$49,"<>") -> 0 | D78: =COUNTIF(Dataset!$W$2:$W$49,$A78) -> 0
A80: Loss Basis | B80: Incidents | C80: Total gross loss (USD)
A81: Bridge-held assets withdrawn | B81: =COUNTIF(Dataset!$X$2:$X$49,$A81) -> 32 | C81: =SUMIFS(Dataset!$F$2:$F$49,Dataset!$X$2:$X$49,$A81) -> 1374824000
A82: Wallet funds drained (approvals or redirection) | B82: =COUNTIF(Dataset!$X$2:$X$49,$A82) -> 7 | C82: =SUMIFS(Dataset!$F$2:$F$49,Dataset!$X$2:$X$49,$A82) -> 18806693
A83: Value of unbacked minted assets | B83: =COUNTIF(Dataset!$X$2:$X$49,$A83) -> 3 | C83: =SUMIFS(Dataset!$F$2:$F$49,Dataset!$X$2:$X$49,$A83) -> 1184000000
A84: Real assets obtained with unbacked tokens | B84: =COUNTIF(Dataset!$X$2:$X$49,$A84) -> 3 | C84: =SUMIFS(Dataset!$F$2:$F$49,Dataset!$X$2:$X$49,$A84) -> 84200000
A85: Reported figure; basis not specified | B85: =COUNTIF(Dataset!$X$2:$X$49,$A85) -> 3 | C85: =SUMIFS(Dataset!$F$2:$F$49,Dataset!$X$2:$X$49,$A85) -> 13800000
A86: Total | B86: =SUM(B81:B85) -> 48 | C86: =SUM(C81:C85) -> 2675630693 | F86: =IF(B86=$B$4,"OK — reconciles","CHECK — does not reconcile") -> OK — reconciles

Sheet Excluded Incidents
A1: Date (as reported) | B1: Victim Platform | C1: Loss (as reported) | D1: Attack Pattern & Root Cause | E1: Source 1 | F1: Source 2 | G1: Source 3 | H1: Attack Pattern (as previously coded) | I1: Functional Domain (remapped) | J1: Reason (as previously coded) | K1: Exclusion Category | L1: Exclusion Rationale
A2: 2025-10-30 | B2: Garden Finance | C2: $11.4 million | D2: A compromise of a third-party "solver" operator, not the core protocol. Garden's non-custodial design routes swaps through independent solver operators. An attacker got hold of a solver's SSH key, gained root access to its server, and found a private key sitting in an environment variable — then drained that solver's own balances across multiple chains. Garden's core bridge contracts and other users' funds were technically unaffected since solvers are architecturally isolated, but the loss was real and significant. | E2: https://garden.finance/blog/garden-incident-report-october-30-2025 | F2: https://www.theblock.co/press-releases/387636/garden-finance-shares-forensic-findings-security-breach-limited-to-solver-layer | G2: https://decrypt.co/356301/garden-finance-shares-forensic-findings-security-breach-limited-to-solver-layer | H2: Infrastructure Hijacking (IH) | I2: FD-5 Governance & Operations | J2: The attacker breached a solver operator's server infrastructure directly, gaining root access through a compromised SSH key, and only then discovered a private key sitting in an environment variable on that compromised machine. Breaching the underlying server infrastructure itself, rather than phishing or socially engineering a specific individual out of their key, is the Infrastructure Hijacking pattern, and for this we have mapped it to Infrastructure Hijacking (IH). Server and cloud infrastructure hosting a bridge operator's secrets falls under the same supporting off-chain infrastructure this domain covers, so for this we have mapped it to FD-5 Governance & Operations. | K2: Out of scope — no bridge loss | L2: Garden's own incident report states no protocol contracts were compromised and no user funds were at risk; the ~$11.4M were an independent solver's own assets. Mention in text as cross-chain infrastructure risk if useful, but not counted in bridge-loss statistics.
A3: 2024-04-30 | B3: Pike Finance (2nd incident) | C3: ~$1.68 Million | D3: After the first CCTP exploit, Pike paused its contracts and shipped an emergency upgrade that added pause() and unpause() functions to the proxy. Those new functions only needed one bit of storage each, but the upgrade assigned them in a way that collided with and overwrote the existing initialized flag, resetting it to its default false value. Four days later, the attacker noticed the contract now looked uninitialized, called its initialize function a second time to set themselves as an active/authorized address, then used that status to call upgradeToAndCall and push their own malicious implementation, draining roughly 479 ETH plus ARB and OP tokens. | E3: https://mirror.xyz/pikefinance.eth/klLV4rRqNYxjRQp0NAfVLboLYtX98P9iYOOf06FUapg | F3: https://www.certik.com/blog/pike-finance-incident-analysis | H3: Logic Exploitation (LE) | I3: FD-4 Execution | J3: The emergency patch deployed after the first incident added new pause and unpause functions that shifted the contract's storage layout, silently resetting the initialized flag back to its default, and the attacker exploited that collision to reinitialize the contract and grant themselves admin rights. A storage-layout bug in the contract's own upgrade logic, exploited by using the contract exactly as the flawed code allowed, is the Logic Exploitation pattern, and for this we have mapped it to Logic Exploitation (LE). The flaw let the attacker execute a privileged withdrawal through the contract's own execution path, so for this we have mapped it to FD-4 Execution. | K3: Out of scope — non-bridge component | L3: Storage-layout collision in Pike's emergency proxy upgrade (re-initialisation of a lending contract). The exploited component is not a bridge or cross-chain messaging mechanism. (Pike 1st incident, which exploited CCTP message validation, is retained.)
A4: 2023-11-22 | B4: KyberSwap | C4: $54.7 Million | D4: Precision Loss: Incorrect rounding in the SwapMath contract's estimateIncrementalLiquidity function caused tick-crossing logic to double-count liquidity at empty tick ranges the attacker deliberately set up, draining low-liquidity pools across 6 chains. | E4: https://blog.kyberswap.com/post-mortem-kyberswap-elastic-exploit/ | F4: https://blocksecteam.medium.com/yet-another-tragedy-of-precision-loss-an-in-depth-analysis-of-the-kyberswap-incident-b0556022a570 | G4: https://www.certik.com/blog/kyberswap-elastic | H4: Logic Exploitation (LE) | I4: FD-4 Execution | J4: The root cause is a precision-loss/rounding bug in the SwapMath contract's estimateIncrementalLiquidity function, which caused the tick-crossing logic to double-count liquidity at empty tick ranges the attacker had deliberately set up. The contract executed its own flawed arithmetic exactly as written, no credential was stolen and no forged proof was submitted. A structural coding flaw exploited by using the contract exactly as designed is the Logic Exploitation pattern, and for this we have mapped it to Logic Exploitation (LE). The flawed calculation lives inside the swap-execution path that directly moves pool liquidity, so for this we have mapped it to FD-4 Execution. | K4: Out of scope — non-bridge component | L4: Rounding/precision bug in the KyberSwap Elastic AMM swap math. Multi-chain deployment and separate bridge integrations do not make the AMM exploit a bridge incident.
A5: 2023-11-10 | B5: Poloniex | C5: $126 Million | D5: Key Compromise: Suspected Lazarus Group attack drained hot wallet private keys across Ethereum, Tron, and Bitcoin. | E5: https://www.coindesk.com/business/2023/11/10/poloniex-hot-wallets-hacked-65m-seemingly-stolen-on-chain-data | F5: https://www.certik.com/blog/poloniex-incident-analysis | G5: https://cointelegraph.com/news/poloniex-hacker-identity-confirmed-10-million-bounty | H5: Credential Seizure (CS) | I5: FD-5 Governance & Operations | J5: Suspected Lazarus Group actors obtained the private keys controlling Poloniex's Ethereum, Tron, and Bitcoin hot wallets and used them to authorize withdrawals the exchange's systems had no way of distinguishing from legitimate operator activity. Using a genuinely stolen signing credential to move funds, rather than exploiting a code flaw, is the Credential Seizure pattern, and for this we have mapped it to Credential Seizure (CS). Hot-wallet signing keys sit in the same persistent custodial control plane as bridge validator keys, so for this we have mapped it to FD-5 Governance & Operations. | K5: Out of scope — centralized exchange | L5: Centralized-exchange hot-wallet private-key compromise. No bridge or cross-chain messaging mechanism involved.
A6: 2023-09-23 | B6: Mixin Network | C6: $200 Million | D6: Cloud Provider Hack: Attackers breached the database of Mixin Network's cloud service provider, exposing custody-layer material and enabling unauthorized withdrawal of network assets. | E6: https://techcrunch.com/2023/09/25/hackers-steal-200-million-from-crypto-company-mixin/ | F6: https://www.elliptic.co/insights/mixin-network-hacked-for-200-million/ | G6: https://www.reuters.com/technology/hong-kong-crypto-firm-hit-by-200-million-hack-2023-09-25/ | H6: Infrastructure Hijacking (IH) | I6: FD-5 Governance & Operations | J6: The attacker breached the database of Mixin Network's cloud infrastructure provider directly, rather than phishing a specific individual or exploiting an on-chain contract, exposing the custody-layer material needed to move network assets. Compromising the underlying cloud/database infrastructure itself is the Infrastructure Hijacking pattern, and for this we have mapped it to Infrastructure Hijacking (IH). Cloud infrastructure hosting a network's custody and signing material falls under the same supporting off-chain infrastructure this domain covers, so for this we have mapped it to FD-5 Governance & Operations. | K6: Out of scope — custodial network infrastructure | L6: Compromise of Mixin's cloud service provider database (custodial hot-wallet material). The exploited component cannot be tied to a bridge transfer/verification mechanism; under a bridge-only inclusion rule it is excluded.
A7: 2023-09-04 | B7: Stake.com | C7: $41.3 Million | D7: Key Exploit: Unauthorized transactions drained ETH/BSC/Polygon hot wallets; the FBI attributed the theft to North Korea's Lazarus Group. Stake's co-founder said a transaction-authorization service, not raw private keys, was the compromised component. | E7: https://medium.com/@edcraven22/always-moving-forward-reflections-on-the-recent-stake-com-exploit-431105710a2e | F7: https://www.fbi.gov/news/press-releases/fbi-identifies-lazarus-group-cyber-actors-as-responsible-for-theft-of-41-million-from-stakecom | G7: https://www.halborn.com/blog/post/explained-the-stake-com-hack-september-2023 | H7: Credential Seizure (CS) | I7: FD-5 Governance & Operations | J7: Attackers gained unauthorized access to the signing/authorization layer behind Stake.com's ETH, BSC, and Polygon hot wallets and used it to move funds out with no interaction with any smart contract; the FBI attributed the theft to the Lazarus Group. Using compromised signing access to authorize a transaction, rather than exploiting a code flaw, is the Credential Seizure pattern, and for this we have mapped it to Credential Seizure (CS). Hot-wallet signing credentials are part of the persistent operational control plane, so for this we have mapped it to FD-5 Governance & Operations. | K7: Out of scope — centralized platform | L7: Theft from an online casino/betting platform's hot wallets (FBI: Lazarus). Funds moving across several chains does not make it a bridge attack.
A8: 2023-03-15 | B8: Poolz Finance | C8: $0.665 Million | D8: Integer Overflow: The CreateMassPools function's getArraySum summation overflowed uint256 in the unaudited LockedControl.sol vesting contract, letting the attacker record a deposit far larger than what was actually transferred, then withdraw the inflated balance. | E8: https://blog.solidityscan.com/poolz-finance-hack-analysis-still-experiencing-overflow-fcf35ab8a6c5/ | F8: https://www.numencyber.com/poolz-finance-attacked-for-665k/ | G8: https://www.ironblocks.com/blog/poolz-protocol-hack-description | H8: Logic Exploitation (LE) | I8: FD-4 Execution | J8: The root cause is an arithmetic overflow in the unaudited LockedControl.sol vesting contract's getArraySum function: passing values that summed past uint256's ceiling wrapped the total to a tiny number, letting the attacker record a deposit far larger than what was actually transferred. The contract executed this flawed arithmetic exactly as written, no credential was stolen and no forged proof was submitted. A structural coding flaw exploited by using the contract exactly as designed is the Logic Exploitation pattern, and for this we have mapped it to Logic Exploitation (LE). The flawed calculation lives inside the function that actually executes the token withdrawal, so for this we have mapped it to FD-4 Execution. | K8: Out of scope — non-bridge component | L8: Integer overflow in Poolz Finance's LockedControl token-vesting/locker contract. The exploited component is not a bridge or cross-chain messaging mechanism.
A9: 2021-11-01 | B9: PolkaBridge | C9: $0.6 Million | D9: Balance Logic: Manual removal of a necessary balance check. | H9: Logic Exploitation (LE) | I9: FD-4 Execution | K9: Outside study period | L9: Incident predates the Jan 2022 – Aug 2026 study period. May be cited as a historical example, not as part of the empirical dataset.
A10: 2021-09-19 | B10: pNetwork | C10: $13 Million | D10: Fake Event Emission: Attacker generated counterfeit events to access Bitcoin; bridge failed to confirm legitimacy. | E10: https://halborn.com/explained-the-pnetwork-hack-september-2021/ | H10: Event Injection (EI) | I10: FD-1 Deposit | K10: Outside study period | L10: Incident predates the Jan 2022 – Aug 2026 study period. May be cited as a historical example, not as part of the empirical dataset.
A11: 2021-08-10 | B11: Poly Network | C11: $611 Million | D11: Unchecked Permission: Unsafe external call allowed attacker to brute-force method variables and change public keys. | E11: https://immunefi.com/blog/bug-fix-reviews/common-cross-chain-bridge-vulnerabilities/ | H11: Logic Exploitation (LE) | I11: FD-4 Execution | K11: Outside study period | L11: Incident predates the Jan 2022 – Aug 2026 study period. May be cited as a historical example, not as part of the empirical dataset.
A12: 2021-07-10 | B12: ChainSwap | C12: $8 Million | D12: Invalid Signature: Exploit caused by insufficient signature verification during the bridge's minting process. | E12: https://arxiv.org/abs/2312.12573 | H12: Proof Forgery (PF) | I12: FD-3 Verification | K12: Outside study period | L12: Incident predates the Jan 2022 – Aug 2026 study period. May be cited as a historical example, not as part of the empirical dataset.
A13: June-July 2021 | B13: THORChain | C13: $16.35 Million | D13: Fake Event Emission: Three consecutive attacks involving faked deposit events to mint or release assets. | E13: https://slowmist.medium.com/slowmist-analysis-of-three-consecutive-attacks-o [URL truncated in source workbook — needs repair if cited] | H13: Event Injection (EI) | I13: FD-1 Deposit | K13: Outside study period | L13: Incident predates the Jan 2022 – Aug 2026 study period. May be cited as a historical example, not as part of the empirical dataset.

Sheet Codebook
A1: SCOPE & INCLUSION
A2: Study period | B2: 1 January 2022 – 31 August 2026 (incident start date).
A3: Unit of analysis | B3: One exploit incident against a cross-chain bridge or cross-chain messaging mechanism. Repeat attacks on the same bridge are separate records.
A4: Inclusion rule | B4: The exploited component must be part of a cross-chain bridge or cross-chain messaging mechanism (deposit/lock/burn handling, relaying, proof/message verification, release/mint execution, or the bridge's own keys, governance, deployment or operating infrastructure). Multi-chain deployment of an otherwise single-chain application, or funds being moved across chains after a theft, does not qualify.
A5: Exclusions | B5: Centralized exchanges and custodial platforms (e.g., Poloniex, Stake.com, Mixin); non-bridge components of protocols that also offer bridging (e.g., KyberSwap Elastic AMM, Poolz locker, Pike upgrade collision); incidents with no loss to the bridge or its users (Garden solver); incidents before 2022. See the Excluded Incidents sheet.
A6: Evidence rule | B6: An incident is included only if supported by an official post-mortem/incident report OR at least two independent technical/reporting sources.
A7: LOSS NORMALIZATION
A8: Gross Bridge-Specific Loss (USD) | B8: Value removed from the bridge, its liquidity, or users via the bridge mechanism, in USD at time of incident. Excludes: unrelated losses at the same organisation (e.g., HTX exchange hot wallets), downstream contagion in third-party protocols (e.g., Kelp rsETH borrowing on lending markets), market/price-impact estimates, and attempted-but-unrealised amounts. Where only a range is reported, the lower bound is used. Recoveries/bounties are not netted out, so the figure is a gross loss and may exceed net losses reported after recovery. When sources disagree, the figure best supported by on-chain evidence or the official report is used, and the choice is explained in the Loss Normalization Note.
A9: ATTACK PATTERNS (one primary per incident)
A10: Event Injection (EI) | B10: A fabricated or unbacked source-side signal (deposit, burn, memo, event) is accepted as a genuine bridge event.
A11: Proof Forgery (PF) | B11: A forged or unbacked proof/message passes, or bypasses, the bridge's verification of cross-chain state (signature, Merkle proof, DVN/oracle attestation, peer trust).
A12: Logic Exploitation (LE) | B12: A structural coding flaw (missing check, initialisation/upgrade bug, arithmetic error, replay) is exploited by using the contract exactly as written, without forging proofs or stealing keys.
A13: Economic-State Manipulation (ESM) | B13: The attacker distorts economic state the bridge depends on (pool balances, internal pricing, stake weight) and extracts value from the distortion. Flash loans are treated as an enabling mechanism, not as the pattern. Replaces the former Flash Loan Amplification (FLA) label.
A14: Credential Seizure (CS) | B14: Genuine signing/admin/deployer/validator credentials are stolen or reconstructed and used to authorise actions the bridge cannot distinguish from legitimate ones.
A15: Infrastructure Hijacking (IH) | B15: The bridge's off-chain operating infrastructure (CI/CD, servers, frontend hosting, DNS/BGP) is compromised to inject capability or redirect users.
A16: PRIMARY FUNCTIONAL DOMAIN (one per incident)
A17: FD-1 Deposit | B17: Sequential execution path, step 1: recognising a source-chain lock, burn or deposit.
A18: FD-2 Relay | B18: Sequential execution path, step 2: off-chain or on-chain relaying/attestation of the cross-chain message.
A19: FD-3 Verification | B19: Sequential execution path, step 3: destination-side verification of the message/proof.
A20: FD-4 Execution | B20: Sequential execution path, step 4: release, mint or withdrawal execution and the accounting it relies on.
A21: FD-5 Governance & Operations | B21: Not a lifecycle step. Persistent governance/operational control plane: keys, multisigs, validator sets, admin/upgrade rights, deployment and hosting infrastructure.
A22: EVIDENCE LEVEL
A23: E1 | B23: Official post-mortem/incident report (or official fix artefact) plus at least one independent technical source.
A24: E2 | B24: At least two independent technical/reporting sources; no official post-mortem linked.
A25: E3 | B25: Single authoritative source — the official post-mortem/incident report only (satisfies the evidence rule).
A26: E4 | B26: On-chain tracing plus third-party reporting; root cause not officially disclosed, so the pattern/domain classification is inferred.
A28: CLASSIFICATION QUALITY FIELDS
A29: Counting rule | B29: Each incident has exactly one primary attack pattern and one primary functional domain, so counts and losses are mutually exclusive and sum to the dataset totals.
A30: Enabling Mechanism | B30: Supporting method recorded separately from the attack pattern (e.g., flash loan, phishing, social engineering). Only mechanisms explicitly stated in the root-cause description are recorded; otherwise 'None recorded'. An enabling mechanism never creates a separate pattern label.
A31: Boundary Case | B31: 'Yes' if, during coding, two patterns each met a necessary condition and the primary pattern had to be chosen with a decision rule (see paper, Boundary Cases table). Six incidents meet this criterion.
A32: Alternative Pattern / Domain | B32: For boundary cases only: the most plausible alternative label. Used in the sensitivity analysis (all 2^6 = 64 combinations of original and alternative labels).
A33: Classification Confidence | B33: Rule-based (live formula): Low = E4 (root cause inferred); Medium = boundary case or E3 (single official source); High = all other incidents.
A34: Coder 2 fields | B34: Columns V and W are left blank for an independent second coder. The second coder should label every incident from the evidence and the classification criteria without viewing columns M, N, O, S or T. Agreement and Cohen's kappa are calculated automatically on the Summary sheet.
A35: Summary statistics | B35: Quartiles in the paper use linear interpolation. The Gini coefficient is computed over the 48 incident-level gross bridge-specific losses (no zero-loss incidents) as the mean absolute difference divided by twice the mean.
A36: Loss Basis | B36: Records what the gross loss figure measures, derived from the existing root-cause and loss notes: Bridge-held assets withdrawn (vaults, escrow, reserves or bridge liquidity); Wallet funds drained (user or team wallets via approvals, or user payments redirected); Value of unbacked minted assets (tokens minted without backing, valued at the time of the incident, even if later frozen); Real assets obtained with unbacked tokens (sale or borrowing proceeds); Reported figure, basis not specified. Bases differ for unbacked-minting incidents; see paper, Loss Measurement.

Sheet Change Log
A1: Issue | B1: Change made
A2: FLA → ESM | B2: Attack Pattern changed to Economic-State Manipulation (ESM) for Allbridge Core (Jul 2026), Shibarium (Sep 2025) and Allbridge (Apr 2023); rationale text rewritten so it no longer refers to Flash Loan Amplification and frames the flash loan as an enabler.
A3: 2021 contamination | B3: PolkaBridge, pNetwork, Poly Network, ChainSwap and THORChain (2021) moved to Excluded Incidents (outside study period); their old ST-x codes remapped to FD-x there for consistency.
A4: Non-bridge incidents | B4: Poloniex, Stake.com, KyberSwap Elastic moved to Excluded Incidents per the reviewer. By the same inclusion rule, Poolz Finance (locker-contract overflow) and Pike Finance 2nd incident (proxy-upgrade storage collision) were also excluded — both exploited non-bridge components. Review these two if you disagree; restoring them is a copy-paste.
A5: Cross-chain vs bridge scope | B5: Bridge-only scope adopted and written into the Codebook. Mixin excluded (cloud-provider compromise of custodial material, not a bridge mechanism). Garden excluded (solver-owned assets; no protocol or user loss per Garden's report).
A6: Loss normalization | B6: New numeric column "Bridge-Specific Loss (USD)" plus a note column. HECO now counts $86.8M bridge loss only (HTX exchange losses removed from figure and from the rationale). Kelp counts the $292M bridge drain only. Sandbox counts the ~$697K direct drain. Across counts the $4.5M paid out. Ranges use the lower bound.
A7: Terminology | B7: "Primary Lifecycle Stage" renamed "Primary Functional Domain"; "Reason (Why This Pattern & Stage)" renamed accordingly; two rationales that said "stage" reworded. Codebook defines FD-1–FD-4 as the sequential path and FD-5 as the control plane.
A8: Evidence structure | B8: New "Evidence Level" column (E1–E4) for every record and a Scope / Evidence Note for borderline rows. Saga previously had one source (Halborn) and did not meet the evidence rule; The Block report added as Source 2. TeleSwap flagged E4 (root cause undisclosed).
A9: Other cleanup | B9: Dates normalised to real dates (ranges use start date, noted); Year column added; stable IDs (BR-001…); Verus repeat-attack text no longer refers to "incident #8 above"; Hyperbridge root-cause label "Admin Permission Takeover" changed to "Proof Verification Flaw" to match its own description and PF code; truncated THORChain 2021 URL flagged.
A10: Dataset count | B10: 60 rows → 55 in study period → 48 bridge-only incidents. The paper's "44" must be updated to 48 (or the 4-incident difference explicitly justified).
A11: Domain labels | B11: FD-3 Verification → FD-3 Verification; FD-4 Execution → FD-4 Execution; FD-5 Governance & Operations → FD-5 Governance & Operations (Dataset, Excluded Incidents, Summary, Codebook) to match the paper.
A12: Loss terminology | B12: Column F renamed 'Gross Bridge-Specific Loss (USD)'; Summary and Codebook updated to state that recoveries are not subtracted. Values unchanged.
... A18: Loss basis | B18: New column X records the basis of each gross loss figure (5 categories) from the existing notes; Summary sheet reports counts and totals by basis. Loss values unchanged.
